{"d":{"100901017":{"i":"7mcppdsajilRCNv5gIWxJn","is":"INU100901017","n":"Hum Tere Shahar Mein Aaye Hain","a":[{"i":"62mCohf6aiF3nryWghwCxM","n":"Ghulam Ali"}],"p":38,"r":"1996-01-01","l":"Ultra","im":"https://i.scdn.co/image/ab67616d0000b2738d1d41e778b5c81b41e63e5b","ps":[{"i":"37i9dQZF1DWUhFTn3RqwnT","n":27,"a":1604392056000,"p":82}],"pp":82},"100901018":{"i":"3s79nxNEpvd3bg80wujSs7","is":"INU100901018","n":"Itna Toota Houn Ke Chhoone Se","a":[{"i":"62mCohf6aiF3nryWghwCxM","n":"Ghulam Ali"}],"p":27,"r":"1996-01-01","l":"Ultra","im":"https://i.scdn.co/image/ab67616d0000b2738d1d41e778b5c81b41e63e5b","ps":[{"i":"37i9dQZF1DWUhFTn3RqwnT","n":48,"a":1604392056000,"p":66}],"pp":66},"101205630":{"i":"00ICosJl0qSeZOdOTCSxxW","is":"INU101205630","n":"Aanu Kashi Hila Mi Nandayala","a":[{"i":"5XcCcaKubEbz1ECA5II7Uy","n":"Vijay Sartape"}],"p":8,"r":"2000-01-01","l":"Ultra Media And Entertainment Pvt Ltd","im":"https://i.scdn.co/image/ab67616d0000b2731860af7fb9b6abf33cfb99a5","ps":[{"i":"37i9dQZF1DX2BZbIB5F2kv","n":25,"a":1603785398000,"p":18}],"pp":18},"101209104":{"i":"40UvbQlegx63rSdfrdSm4e","is":"INU101209104","n":"Chala Javu Jejurila Khandrayacha","a":[{"i":"3ePSkH2xyv0ZHEyVEfQbB8","n":"Shakuntala Jadhav"}],"p":12,"r":"2005-01-01","l":"Ultra Media And Entertainment Pvt Ltd","im":"https://i.scdn.co/image/ab67616d0000b2734c32f59a577758c5627cb383","ps":[{"i":"37i9dQZF1DX2BZbIB5F2kv","n":23,"a":1603785398000,"p":18}],"pp":18},"101212435":{"i":"5phS7prVq4sjhnB54u7tv6","is":"INU101212435","n":"Dhagala Lagali Kal","a":[{"i":"4YZKsoKCXCaCppcmP729EY","n":"Shrikant Narayan"}],"p":28,"r":"2008-01-01","l":"Ultra Media And Entertainment Pvt Ltd","im":"https://i.scdn.co/image/ab67616d0000b273c62ea04d64de5d065f425f63","ps":[{"i":"37i9dQZF1DWZPrKPHbO4OG","n":32,"a":1604909328000,"p":37},{"i":"37i9dQZF1DXbDnhbYgHWVw","n":10,"a":1605339597000,"p":7}],"pp":44},"101213494":{"i":"5EwEndeTEguoTWdMa2WCl7","is":"INU101213494","n":"Waat Maji Baghtoy Rikshawala","a":[{"i":"0us5qLUz4waTwJ7hGoBrxl","n":"Reshma Sonawane"}],"p":35,"r":"2012-01-01","l":"Ultra","im":"https://i.scdn.co/image/ab67616d0000b2730f125963b3021229d6539760","ps":[{"i":"37i9dQZF1DX84EApEEEkUc","n":47,"a":1605339567000,"p":86},{"i":"37i9dQZF1DX32ZhGstc1pA","n":10,"a":1603558482000,"p":83},{"i":"37i9dQZF1DXdAS31iLwf91","n":56,"a":1604555466000,"p":28},{"i":"37i9dQZF1DXbDnhbYgHWVw","n":14,"a":1605339597000,"p":7}],"pp":204},"101600210":{"i":"3pHLwwxM7nEUBxbxYNE5LI","is":"INU101600210","n":"Aai Bharosa Thev Aamche Koli Lokava","a":[{"i":"1IDS6NfsM6J0yM0LeTwCYU","n":"Kesari Vitthal Saudicha"}],"p":13,"r":"2016-01-10","l":"Ultra Media And Entertainment Pvt Ltd","im":"https://i.scdn.co/image/ab67616d0000b273b1fca50104500f3022a11330","ps":[{"i":"37i9dQZF1DWUhwij7QJy68","n":34,"a":1605167332000,"p":18}],"pp":18},"101900049":{"i":"24luJ4DfikNNdmGi8b0I8Y","is":"INU101900049","n":"Melyan Takun Thevalay Gala","a":[{"i":"7BJwmRulLj8eQeJCdutPOH","n":"Chandan Kamble"},{"i":"4m1ngCnmOfr4rESFqgTXco","n":"Amruta Dahivelkar"}],"p":8,"r":"2019-04-05","l":"Ultra","im":"https://i.scdn.co/image/ab67616d0000b273269763a669425d74ab014b89","ps":[{"i":"37i9dQZF1DX2BZbIB5F2kv","n":29,"a":1603785398000,"p":17}],"pp":17},"110800764":{"i":"4M0HVS8WwKyPlEgLUJZ8wU","is":"INU110800764","n":"OM CHANTS","a":[{"i":"7qmDhVWCrIHIvIAo7b7KTa","n":"Rajkumar Bharathi"}],"p":24,"r":"2008","l":"Unique Recording Co.","im":"https://i.scdn.co/image/ab67616d0000b273e9f82d7c042bda5f29257dbe","ps":[{"i":"37i9dQZF1DXd9Uz5V4eZsn","n":42,"a":1602761924000,"p":81}],"pp":81},"151200098":{"i":"4GagsETs7qfR3cwQkRcXgb","is":"INU151200098","n":"Main Kya Karoon","a":[{"i":"1wRPtKGflJrBx9BmLsSwlU","n":"Pritam"},{"i":"7HHLBC9hUb55SDUcBlM8FQ","n":"Nikhil Paul George"}],"p":51,"r":"2012-06-24","l":"UTV","im":"https://i.scdn.co/image/ab67616d0000b2730ca93f934628024dc6573e59","ps":[{"i":"37i9dQZF1DXd05hd2jmMZL","n":31,"a":1601781785000,"p":150},{"i":"37i9dQZF1DWVDvBpGQbzXj","n":71,"a":1602827504000,"p":78}],"pp":228},"151200111":{"i":"7ttlemwytO21npSmLKqTBg","is":"INU151200111","n":"Aashiyan","a":[{"i":"1wRPtKGflJrBx9BmLsSwlU","n":"Pritam"},{"i":"0oOet2f43PA68X5RxKobEy","n":"Shreya Ghoshal"},{"i":"7HHLBC9hUb55SDUcBlM8FQ","n":"Nikhil Paul George"}],"p":51,"r":"2012-06-24","l":"UTV","im":"https://i.scdn.co/image/ab67616d0000b2730ca93f934628024dc6573e59","ps":[{"i":"37i9dQZF1DWTwbZHrJRIgD","n":35,"a":1603861694000,"p":147}],"pp":147},"151200113":{"i":"1sYC1fG7s4p0pTykrJqmgW","is":"INU151200113","n":"Kyon","a":[{"i":"1wRPtKGflJrBx9BmLsSwlU","n":"Pritam"},{"i":"2FPwX3Gh0w4Qr1v3zSTtcT","n":"Papon"},{"i":"3eDT9fwXKuHWFvgZaaYC5v","n":"Sunidhi Chauhan"}],"p":57,"r":"2012-06-24","l":"UTV","im":"https://i.scdn.co/image/ab67616d0000b2730ca93f934628024dc6573e59","ps":[{"i":"37i9dQZF1DWSwxyU5zGZYe","n":41,"a":1605269570000,"p":200}],"pp":200},"151200114":{"i":"7fpWJr5shT90KiCHXKHxch","is":"INU151200114","n":"Phir Le Aya Dil - Reprise","a":[{"i":"1wRPtKGflJrBx9BmLsSwlU","n":"Pritam"},{"i":"4YRxDV8wJFPHPTeXepOstw","n":"Arijit Singh"}],"p":58,"r":"2012-06-24","l":"UTV","im":"https://i.scdn.co/image/ab67616d0000b2730ca93f934628024dc6573e59","ps":[{"i":"37i9dQZF1DWSoLBQNkZBKc","n":34,"a":1605167653000,"p":173}],"pp":173},"151200117":{"i":"4I5Xcdu5Hnki1aP0Uxbs4n","is":"INU151200117","n":"Saawali Si Raat","a":[{"i":"1wRPtKGflJrBx9BmLsSwlU","n":"Pritam"},{"i":"4YRxDV8wJFPHPTeXepOstw","n":"Arijit Singh"}],"p":52,"r":"2012-06-24","l":"UTV","im":"https://i.scdn.co/image/ab67616d0000b2730ca93f934628024dc6573e59","ps":[{"i":"37i9dQZF1DWX3SoTqhs2rq","n":14,"a":1602147936000,"p":219}],"pp":219},"151200172":{"i":"641bXdF0Ho7wkGZaSCXu4s","is":"INU151200172","n":"Motorwada","a":[{"i":"7HCqGPJcQTyGJ2yqntbuyr","n":"Amit Trivedi"},{"i":"6k6dimE4a6OFnD0HWmkIUW","n":"Tochi Raina"}],"p":34,"r":"2012-06-24","l":"UTV","im":"https://i.scdn.co/image/ab67616d0000b273c675042a28be1a27e4f9e8d8","ps":[{"i":"37i9dQZF1DXd05hd2jmMZL","n":37,"a":1601781785000,"p":141}],"pp":141},"151200174":{"i":"4a95VZJzjMWNJlwuIPzhsI","is":"INU151200174","n":"KikliKalerdi","a":[{"i":"7HCqGPJcQTyGJ2yqntbuyr","n":"Amit Trivedi"},{"i":"2umaOFeLVYvdsDfmhhlmuf","n":"Pinky Maidasani"},{"i":"7uIbLdzzSEqnX0Pkrb56cR","n":"Yo Yo Honey Singh"}],"p":31,"r":"2012-06-24","l":"UTV","im":"https://i.scdn.co/image/ab67616d0000b273c675042a28be1a27e4f9e8d8","ps":[{"i":"37i9dQZF1DXd05hd2jmMZL","n":36,"a":1601781785000,"p":142}],"pp":142},"151300003":{"i":"6iFm1CcTrJe7SbZqXMXuDk","is":"INU151300003","n":"Meethi Boliyaan","a":[{"i":"7HCqGPJcQTyGJ2yqntbuyr","n":"Amit Trivedi"},{"i":"4aR25YYg7R0ROZi1VJ5ONE","n":"Mili Nair"}],"p":46,"r":"2013-02-01","l":"UTV","im":"https://i.scdn.co/image/ab67616d0000b27323e6191c62510fcea15b0dd6","ps":[{"i":"37i9dQZF1DXbUXk0Of9cjw","n":29,"a":1602829753000,"p":64}],"pp":64},"151400121":{"i":"57TekJn37PJuZyHoVP1bgM","is":"INU151400121","n":"Gulon Mein Rang Bhare","a":[{"i":"4YRxDV8wJFPHPTeXepOstw","n":"Arijit Singh"}],"p":44,"r":"2014-09-15","l":"Times Music","im":"https://i.scdn.co/image/ab67616d0000b2730a93baccccffd0eecb2b9baf","ps":[{"i":"37i9dQZF1DWSoLBQNkZBKc","n":6,"a":1605167653000,"p":229}],"pp":229}},"s":["m","2"]}