{"d":{"200825":{"i":"0Qpdo9lUFMy538k4lzNURQ","is":"USWB10200825","n":"You Gotta Get It While You Can","a":[{"i":"7aRi9OzdA2ciputfuguaPK","n":"Larry Carlton"}],"p":34,"r":"1982","l":"Rhino/Warner Records","im":"https://i.scdn.co/image/ab67616d0000b273220b440ccf3100c79c39eabf","ps":[{"i":"37i9dQZF1DX0aSJooo0zWR","n":54,"a":1604635260000,"p":197}],"pp":197},"200887":{"i":"0ccCwNzXvr1Yoz91vKz31Z","is":"USWB10200887","n":"Yoshimi Battles the Pink Robots, Pt. 1","a":[{"i":"16eRpMNXSQ15wuJoeqguaB","n":"The Flaming Lips"}],"p":62,"r":"2002-05-13","l":"Warner Records","im":"https://i.scdn.co/image/ab67616d0000b273ca69f52416a728ebd0b9103c","ps":[{"i":"37i9dQZF1DX11WWTNSp4Dq","n":702,"a":1544887740000,"p":0}],"pp":0},"200893":{"i":"2DFRFqWNahKtFD112H2iEZ","is":"USWB10200893","n":"Do You Realize??","a":[{"i":"16eRpMNXSQ15wuJoeqguaB","n":"The Flaming Lips"}],"p":64,"r":"2002-05-13","l":"Warner Records","im":"https://i.scdn.co/image/ab67616d0000b273ca69f52416a728ebd0b9103c","ps":[{"i":"37i9dQZF1DX0YKekzl0blG","n":75,"a":1545231521000,"p":332},{"i":"37i9dQZF1DX38lOuCWlLV1","n":6,"a":1602103219000,"p":130},{"i":"37i9dQZF1DXe87nR6LypeT","n":38,"a":1603980897000,"p":17},{"i":"37i9dQZF1DX11WWTNSp4Dq","n":703,"a":1544887740000,"p":0}],"pp":479},"201068":{"i":"2sowiwuhxt4nLIWP6vWJOa","is":"USWB10201068","n":"Paranoid Android","a":[{"i":"2vI9KFm0fwSfPrpEgOeIbq","n":"Brad Mehldau"}],"p":45,"r":"2002-08-13","l":"Nonesuch","im":"https://i.scdn.co/image/ab67616d0000b273a4c3e2ce4bb985d6c4a28f64","ps":[{"i":"37i9dQZF1DWUPafHP1BJw1","n":83,"a":1605240060000,"p":199}],"pp":199},"201201":{"i":"7FtEb0OVMlMrFbHH1dpdul","is":"USWB10201201","n":"Child's Christmas In Wales","a":[{"i":"5MWBg16f5UYiaSlyVhzlIW","n":"John Cale"}],"p":30,"r":"1973-02-25","l":"Domino Recording Co","im":"https://i.scdn.co/image/ab67616d0000b273795ab2f58fc8d94ffd01d5bf","ps":[{"i":"6pHALZfTS7jRs1RxZ6ofGG","n":716,"a":1545224502000,"p":0}],"pp":0},"201206":{"i":"5Zpy2HR2vYLjlTQVd81DLH","is":"USWB10201206","n":"Paris 1919","a":[{"i":"5MWBg16f5UYiaSlyVhzlIW","n":"John Cale"}],"p":56,"r":"1973-02-25","l":"Domino Recording Co","im":"https://i.scdn.co/image/ab67616d0000b273795ab2f58fc8d94ffd01d5bf","ps":[{"i":"37i9dQZF1DXdTCdwCKzXwo","n":63,"a":1544804078000,"p":434},{"i":"37i9dQZF1DX11WWTNSp4Dq","n":653,"a":1544887740000,"p":1},{"i":"6pHALZfTS7jRs1RxZ6ofGG","n":996,"a":1523451376000,"p":0}],"pp":435},"201209":{"i":"2l0Bye8zQItfBm8kWd2F0H","is":"USWB10201209","n":"Antarctica Starts Here","a":[{"i":"5MWBg16f5UYiaSlyVhzlIW","n":"John Cale"}],"p":28,"r":"1973-02-25","l":"Domino Recording Co","im":"https://i.scdn.co/image/ab67616d0000b273795ab2f58fc8d94ffd01d5bf","ps":[{"i":"6pHALZfTS7jRs1RxZ6ofGG","n":436,"a":1569416595000,"p":1}],"pp":1},"201492":{"i":"6uP1ltEgH9Na7C1AkxJTvF","is":"USWB10201492","n":"Gimme Gimme Gimme (with Patti Austin)","a":[{"i":"37WGztoQRbNgo55GQCw75B","n":"Narada Michael Walden"},{"i":"0JxChc2w5fwTGbXKfc4cRd","n":"Patti Austin"}],"p":49,"r":"1985","l":"Rhino/Warner Records","im":"https://i.scdn.co/image/ab67616d0000b2739a6c2a9a01bd09e3cf7c79c6","ps":[{"i":"37i9dQZF1DX0mziTeNtU34","n":142,"a":1594891863000,"p":13}],"pp":13},"201688":{"i":"1f2V8U1BiWaC9aJWmpOARe","is":"USWB10201688","n":"By the Way","a":[{"i":"0L8ExT028jH3ddEcZwqJJ5","n":"Red Hot Chili Peppers"}],"p":74,"r":"2002-07-09","l":"Warner Records","im":"https://i.scdn.co/image/ab67616d0000b273de1af2785a83cc660155a0c4","ps":[{"i":"37i9dQZF1DWUE25YmPdDOO","n":11,"a":1603890352000,"p":113},{"i":"37i9dQZF1DXcSNirXzsHRX","n":69,"a":1603439699000,"p":108},{"i":"37i9dQZF1DWTxGlNb1UxJ3","n":13,"a":1604506450000,"p":12}],"pp":233},"201694":{"i":"3ZOEytgrvLwQaqXreDs2Jx","is":"USWB10201694","n":"Can't Stop","a":[{"i":"0L8ExT028jH3ddEcZwqJJ5","n":"Red Hot Chili Peppers"}],"p":80,"r":"2002-07-09","l":"Warner Records","im":"https://i.scdn.co/image/ab67616d0000b273de1af2785a83cc660155a0c4","ps":[{"i":"37i9dQZF1DX1tyCD9QhIWF","n":28,"a":1604323274000,"p":1034},{"i":"37i9dQZF1DWZUTt0fNaCPB","n":14,"a":1605262318000,"p":724},{"i":"37i9dQZF1DX1te6miphixI","n":38,"a":1605239313000,"p":579},{"i":"37i9dQZF1DWYp5sAHdz27Y","n":58,"a":1605028471000,"p":238},{"i":"37i9dQZF1DX4oL1xd4OWmV","n":3,"a":1604530363000,"p":180},{"i":"37i9dQZF1DWUDDQGPhU1P8","n":99,"a":1603954175000,"p":25},{"i":"37i9dQZF1DWTxGlNb1UxJ3","n":99,"a":1604506450000,"p":5},{"i":"37i9dQZF1DXcAT1rRHjDPE","n":46,"a":1605059258000,"p":4}],"pp":2789},"201729":{"i":"4FzPIalyruWIiefI91qe4B","is":"USWB10201729","n":"Rock 'n' Roll High School - 2002 Remaster","a":[{"i":"1co4F2pPNH8JjTutZkmgSm","n":"Ramones"}],"p":55,"r":"1980-02-04","l":"Rhino/Warner Records","im":"https://i.scdn.co/image/ab67616d0000b2737b15d77c4dc346ce1e444ca2","ps":[{"i":"37i9dQZF1DWWsq4e0rDzty","n":19,"a":1601399863000,"p":56}],"pp":56},"201817":{"i":"6vvmYYUvGXtZLU8msxKvzF","is":"USWB10201817","n":"I Wanna Be Sedated - 2002 Remaster","a":[{"i":"1co4F2pPNH8JjTutZkmgSm","n":"Ramones"}],"p":62,"r":"1978-09-22","l":"Rhino/Warner Records","im":"https://i.scdn.co/image/ab67616d0000b273d8b51e7394e2c2c1aa6eb0cb","ps":[{"i":"37i9dQZF1DWV1Nj8a6volf","n":44,"a":1605297766000,"p":548}],"pp":548},"201881":{"i":"3nDCRsKhV3R53tNEBj4M1S","is":"USWB10201881","n":"Pet Sematary - 2002 Remaster","a":[{"i":"1co4F2pPNH8JjTutZkmgSm","n":"Ramones"}],"p":54,"r":"2006-06-05","l":"Rhino/Warner Records","im":"https://i.scdn.co/image/ab67616d0000b2733d4f45a3be0df9dbef9d9d70","ps":[{"i":"37i9dQZF1DX6SpcerLn1dx","n":32,"a":1602628377000,"p":300}],"pp":300},"201991":{"i":"1AEYT6VxrxXPMoQUxsY0E4","is":"USWB10201991","n":"Headstrong","a":[{"i":"1UdQqCUR7RwB9YYJONwbdM","n":"Trapt"}],"p":74,"r":"2002-11-05","l":"RT Industries","im":"https://i.scdn.co/image/ab67616d0000b27374d9a833744be96426ee833c","ps":[{"i":"37i9dQZF1DXcfZ6moR6J0G","n":26,"a":1601999405000,"p":722},{"i":"37i9dQZF1DX1EBIvjCbIEj","n":74,"a":1604500356000,"p":5}],"pp":727},"202005":{"i":"2oxcmG1trE8AKHE9b14Lvx","is":"USWB10202005","n":"Facts of Love","a":[{"i":"1SaH16LT1AWVsBU8AKY4HN","n":"Jeff Lorber"}],"p":32,"r":"1986","l":"Rhino/Warner Records","im":"https://i.scdn.co/image/ab67616d0000b273ed94b1b5aeb524f3ba1bf730","ps":[{"i":"37i9dQZF1DWZXHVUlGM9Wp","n":32,"a":1603266942000,"p":276}],"pp":276},"202066":{"i":"1qMWonHWe4EnzC2tSL7LVm","is":"USWB10202066","n":"Feliz Navidad","a":[{"i":"4MPkNgar5uTd8Sqvrr7par","n":"Clay Walker"}],"p":22,"r":"2002-09-17","l":"Warner Records/Nashville","im":"https://i.scdn.co/image/ab67616d0000b27329656d13cedfa4e4a9c9f7a5","ps":[{"i":"37i9dQZF1DX2C6Zlz76Dq4","n":18,"a":1604765728000,"p":113}],"pp":113},"202123":{"i":"58DXqHKK7TfxUmhCq2ux4E","is":"USWB10202123","n":"Hard to Say I'm Sorry","a":[{"i":"3iDD7bnsjL9J4fO298r0L0","n":"Chicago"}],"p":57,"r":"2012-10-29","l":"Rhino","im":"https://i.scdn.co/image/ab67616d0000b273c718dc263482608d8b282b0a","ps":[{"i":"37i9dQZF1DWSY75PtDqTkW","n":117,"a":1603793059000,"p":52}],"pp":52},"202697":{"i":"4tPFEWRuNQhibDQSGB2PVE","is":"USWB10202697","n":"Don't Want to Know If You Are Lonely","a":[{"i":"16bN8mhtDFdegWbg0z3s10","n":"Hüsker Dü"}],"p":53,"r":"1986","l":"Rhino/Warner Records","im":"https://i.scdn.co/image/ab67616d0000b273ebea9b0302ededa5932311ca","ps":[{"i":"37i9dQZF1DX33SCWnjHVGD","n":48,"a":1605187041000,"p":19}],"pp":19},"202888":{"i":"7DUpuAzGUyJaJB3p9BC3Ms","is":"USWB10202888","n":"Die Another Day","a":[{"i":"6tbjWDEIzxoDsBA1FuhfPW","n":"Madonna"}],"p":55,"r":"2003-04-22","l":"Warner Records/Maverick","im":"https://i.scdn.co/image/ab67616d0000b273ef1409a4805cee0dd7f78467","ps":[{"i":"37i9dQZF1DWTxGlNb1UxJ3","n":8,"a":1604506450000,"p":13}],"pp":13},"300376":{"i":"3fjmSxt0PskST13CSdBUFx","is":"USWB10300376","n":"Somewhere I Belong","a":[{"i":"6XyY86QOPPrYVGvF9ch6wz","n":"Linkin Park"}],"p":70,"r":"2003-03-24","l":"Warner Records","im":"https://i.scdn.co/image/ab67616d0000b27389a8fab8bf8cd2b77da1fd17","ps":[{"i":"37i9dQZF1DXcfZ6moR6J0G","n":14,"a":1601999405000,"p":815}],"pp":815},"300468":{"i":"4Yf5bqU3NK4kNOypcrLYwU","is":"USWB10300468","n":"Faint","a":[{"i":"6XyY86QOPPrYVGvF9ch6wz","n":"Linkin Park"}],"p":70,"r":"2003-03-24","l":"Warner Records","im":"https://i.scdn.co/image/ab67616d0000b273b4ad7ebaf4575f120eb3f193","ps":[{"i":"37i9dQZF1DX1EBIvjCbIEj","n":77,"a":1604500356000,"p":5}],"pp":5},"300474":{"i":"2nLtzopw4rPReszdYBJU6h","is":"USWB10300474","n":"Numb","a":[{"i":"6XyY86QOPPrYVGvF9ch6wz","n":"Linkin Park"}],"p":82,"r":"2003-03-24","l":"Warner Records","im":"https://i.scdn.co/image/ab67616d0000b273b4ad7ebaf4575f120eb3f193","ps":[{"i":"37i9dQZF1DXcfZ6moR6J0G","n":21,"a":1601999405000,"p":759},{"i":"37i9dQZF1DWXeOurMWUII5","n":20,"a":1605261178000,"p":560},{"i":"37i9dQZF1DWT3pfwRgyQMA","n":15,"a":1605401525000,"p":356},{"i":"37i9dQZF1DX4vth7idTQch","n":97,"a":1601561160000,"p":276},{"i":"37i9dQZF1DXacPj7eARo6k","n":97,"a":1602143066000,"p":228},{"i":"37i9dQZF1DXcSNirXzsHRX","n":18,"a":1603439699000,"p":180},{"i":"37i9dQZF1DX4oL1xd4OWmV","n":4,"a":1604530363000,"p":179},{"i":"37i9dQZF1DWUTyFWTWhXCs","n":63,"a":1605262004000,"p":75},{"i":"37i9dQZF1DXblV99WEHIW4","n":0,"a":1604500820000,"p":71},{"i":"37i9dQZF1DX66oP1KOp0fw","n":65,"a":1605262086000,"p":40},{"i":"37i9dQZF1DXcAT1rRHjDPE","n":50,"a":1605059258000,"p":4}],"pp":2728},"300532":{"i":"5NDS6qHwbOmVqZgTvtC66y","is":"USWB10300532","n":"Love Profusion","a":[{"i":"6tbjWDEIzxoDsBA1FuhfPW","n":"Madonna"}],"p":44,"r":"2003-04-22","l":"Warner Records/Maverick","im":"https://i.scdn.co/image/ab67616d0000b273ef1409a4805cee0dd7f78467","ps":[{"i":"37i9dQZF1DX5PBX3AOpG5l","n":30,"a":1604505977000,"p":10}],"pp":10},"300569":{"i":"6KE4QXE06QDEn7zRFkpxdk","is":"USWB10300569","n":"Don't Know Why","a":[{"i":"3t58jfUhoMLYVO14XaUFLA","n":"Pat Metheny"}],"p":47,"r":"2003","l":"Nonesuch","im":"https://i.scdn.co/image/ab67616d0000b273f67edc70211d55eb08dc5634","ps":[{"i":"37i9dQZF1DWUPafHP1BJw1","n":63,"a":1605240060000,"p":243}],"pp":243},"300636":{"i":"1iD0a0plhO55cWEJa5UGcZ","is":"USWB10300636","n":"The Science of Selling Yourself Short","a":[{"i":"20oQv3LStCKCjI9oQ0JNha","n":"Less Than Jake"}],"p":58,"r":"2003-05-19","l":"Sire/Warner Records","im":"https://i.scdn.co/image/ab67616d0000b27346b71e44bcda9ea6eba4182e","ps":[{"i":"37i9dQZF1DX7WJ4yDmRK8R","n":52,"a":1605319781000,"p":295}],"pp":295},"301244":{"i":"599mXRPZpfTGaecsE1A2OQ","is":"USWB10301244","n":"Smile","a":[{"i":"4xac3zhHlBm5QDxbZeqgeR","n":"Robert Randolph & The Family Band"}],"p":22,"r":"2003-07-22","l":"Warner Records","im":"https://i.scdn.co/image/ab67616d0000b273e1507cb803f66d2d5c907086","ps":[{"i":"37i9dQZF1DXdeoRwG5yUKg","n":66,"a":1604607904000,"p":119}],"pp":119},"301489":{"i":"3pdHJCTk85ls2SGGXIJ7XH","is":"USWB10301489","n":"Fall Back Down","a":[{"i":"6xTk3EK5T9UzudENVvu9YB","n":"Rancid"}],"p":60,"r":"2003-08-19","l":"Epitaph","im":"https://i.scdn.co/image/ab67616d0000b273b4d6e44a1a58a9bdcd1edee7","ps":[{"i":"37i9dQZF1DXdC0xwhATLgu","n":113,"a":1575846120000,"p":40}],"pp":40},"301803":{"i":"35ZmCVnfYRdK1iLGCxNhMa","is":"USWB10301803","n":"The Only","a":[{"i":"7JDSHlDdVTo7aZKdQZ53Vf","n":"Static-X"}],"p":64,"r":"2003-10-07","l":"Warner Records","im":"https://i.scdn.co/image/ab67616d0000b27351e68094dd2b709d70f1778f","ps":[{"i":"37i9dQZF1DWXNFSTtym834","n":13,"a":1603806854000,"p":412}],"pp":412},"301999":{"i":"4G3EKvGtqcUSZqPQIWJFxd","is":"USWB10301999","n":"Gary's Theme - 2003 Remastered Version","a":[{"i":"4jXfFzeP66Zy67HM2mvIIF","n":"Bill Evans"}],"p":0,"r":"1977","l":"Concord Music Group","im":"https://i.scdn.co/image/ab67616d0000b2732ca469533bf60bce379a1285","ps":[{"i":"37i9dQZF1DX4wta20PHgwo","n":59,"a":1603797794000,"p":751},{"i":"37i9dQZF1DWVqfgj8NZEp1","n":103,"a":1602216060000,"p":534},{"i":"37i9dQZF1DX55mNLGdHona","n":60,"a":1604523927000,"p":51}],"pp":1336},"302468":{"i":"6R9LiK1WhfnTvFsVfusdQl","is":"USWB10302468","n":"If I Had a Hammer - 2004 Remaster","a":[{"i":"6yrBBtqX2gKCHCrZOYBDrB","n":"Peter, Paul and Mary"}],"p":48,"r":"2005-08-23","l":"Rhino/Warner Records","im":"https://i.scdn.co/image/ab67616d0000b2732cfb2e0ebce5717447deb069","ps":[{"i":"37i9dQZF1DWVmps5U8gHNv","n":20,"a":1602093761000,"p":561},{"i":"37i9dQZF1DX3uZHsihe90o","n":13,"a":1557508006000,"p":369}],"pp":930},"302473":{"i":"7raciFPVU5VuHmqVbw2c1h","is":"USWB10302473","n":"Puff, the Magic Dragon - 2004 Remaster","a":[{"i":"6yrBBtqX2gKCHCrZOYBDrB","n":"Peter, Paul and Mary"}],"p":51,"r":"2005-08-23","l":"Rhino/Warner Records","im":"https://i.scdn.co/image/ab67616d0000b2732cfb2e0ebce5717447deb069","ps":[{"i":"37i9dQZF1DX3uZHsihe90o","n":6,"a":1557508006000,"p":395},{"i":"37i9dQZF1DWVmps5U8gHNv","n":87,"a":1602093761000,"p":286}],"pp":681},"302628":{"i":"28Zax7vgVaaFmhUvwSsAY0","is":"USWB10302628","n":"A Change at Christmas (Say It Isn't So)","a":[{"i":"16eRpMNXSQ15wuJoeqguaB","n":"The Flaming Lips"}],"p":17,"r":"2010-11-02","l":"Warner Records","im":"https://i.scdn.co/image/ab67616d0000b273b1204dff580c4d6771b441a5","ps":[{"i":"37i9dQZF1DWSt7oHsDTXzj","n":27,"a":1515060229000,"p":223}],"pp":223},"302716":{"i":"2JFUdMdA4HCV7x5mtCs6Ie","is":"USWB10302716","n":"Cruzin'","a":[{"i":"0nxjYR9Lf2pvZWLsQJM8z6","n":"Dan Hicks"}],"p":7,"r":"1978-08-15","l":"Rhino/Warner Records","im":"https://i.scdn.co/image/ab67616d0000b27326f1faf57a51aa592061561a","ps":[{"i":"6pHALZfTS7jRs1RxZ6ofGG","n":463,"a":1568206923000,"p":1}],"pp":1},"302758":{"i":"5s7m2xNZWgz5FqVSIvJcGA","is":"USWB10302758","n":"Save a Horse (Ride a Cowboy)","a":[{"i":"0oBEeN6BCxEgMogzThqrPf","n":"Big & Rich"}],"p":68,"r":"2004-04-20","l":"Warner Records/Nashville","im":"https://i.scdn.co/image/ab67616d0000b273805374f00048ac081460cc70","ps":[{"i":"37i9dQZF1DXdxUH6sNtcDe","n":9,"a":1602337999000,"p":354}],"pp":354},"400046":{"i":"5TDZyWDfbQFQJabbPwImVY","is":"USWB10400046","n":"Dreams - 2004 Remaster","a":[{"i":"08GQAI4eElDnROBrJRGE0X","n":"Fleetwood Mac"}],"p":62,"r":"1977-02-04","l":"Rhino/Warner Records","im":"https://i.scdn.co/image/ab67616d0000b2730001af4f80be77069fc8fd41","ps":[{"i":"37i9dQZF1DXbquP6FLBSJX","n":0,"a":1602738244000,"p":421}],"pp":421},"400047":{"i":"2TJqhMuTx2eMun7MMQVIFy","is":"USWB10400047","n":"Never Going Back Again - 2004 Remaster","a":[{"i":"08GQAI4eElDnROBrJRGE0X","n":"Fleetwood Mac"}],"p":58,"r":"1977-02-04","l":"Rhino/Warner Records","im":"https://i.scdn.co/image/ab67616d0000b2730001af4f80be77069fc8fd41","ps":[{"i":"37i9dQZF1DX9w1Quh8lR7W","n":78,"a":1603187361000,"p":158}],"pp":158},"400050":{"i":"07GvNcU1WdyZJq3XxP0kZa","is":"USWB10400050","n":"Go Your Own Way - 2004 Remaster","a":[{"i":"08GQAI4eElDnROBrJRGE0X","n":"Fleetwood Mac"}],"p":77,"r":"1977-02-04","l":"Rhino/Warner Records","im":"https://i.scdn.co/image/ab67616d0000b2730001af4f80be77069fc8fd41","ps":[{"i":"37i9dQZF1DWTJ7xPn4vNaz","n":69,"a":1597672531000,"p":998},{"i":"37i9dQZF1DWXTHBOfJ8aI7","n":52,"a":1604576249000,"p":352},{"i":"37i9dQZEVXbM8SIrkERIYl","n":49,"a":0,"p":275},{"i":"37i9dQZF1DWXd7abuqiatD","n":29,"a":1602738438000,"p":103}],"pp":1728},"400051":{"i":"2JoUtztTqCN4ZhmbRDGPIL","is":"USWB10400051","n":"Songbird - 2004 Remaster","a":[{"i":"08GQAI4eElDnROBrJRGE0X","n":"Fleetwood Mac"}],"p":63,"r":"1977-02-04","l":"Rhino/Warner Records","im":"https://i.scdn.co/image/ab67616d0000b2730001af4f80be77069fc8fd41","ps":[{"i":"37i9dQZF1DWY373eEGlSj4","n":35,"a":1604911912000,"p":601}],"pp":601},"400054":{"i":"28H3wOEKsaEa8NBEYCLl4j","is":"USWB10400054","n":"You Make Loving Fun - 2004 Remaster","a":[{"i":"08GQAI4eElDnROBrJRGE0X","n":"Fleetwood Mac"}],"p":65,"r":"1977-02-04","l":"Rhino/Warner Records","im":"https://i.scdn.co/image/ab67616d0000b2730001af4f80be77069fc8fd41","ps":[{"i":"37i9dQZF1DXbquP6FLBSJX","n":45,"a":1602738244000,"p":268}],"pp":268},"400213":{"i":"71mDjdeVK9sqXmamMHaAfX","is":"USWB10400213","n":"Some Cut (feat. Cutty)","a":[{"i":"3jahzTuztFVegfKXChatkY","n":"Trillville"},{"i":"3jhkLfgJKRu9Lb0AQd7fkB","n":"Cutty"}],"p":53,"r":"2009-08-21","l":"Reprise","im":"https://i.scdn.co/image/ab67616d0000b273b0c2e9a05d1d51fc21b07c82","ps":[{"i":"37i9dQZF1DWUFmyho2wkQU","n":115,"a":1601999832000,"p":231}],"pp":231},"400218":{"i":"0EgigrGFGb4PHaVNb7fgK7","is":"USWB10400218","n":"No Problem","a":[{"i":"5einkgXXrjhfYCyac1FANB","n":"Lil Scrappy"}],"p":55,"r":"2009-08-21","l":"Reprise","im":"https://i.scdn.co/image/ab67616d0000b273b0c2e9a05d1d51fc21b07c82","ps":[{"i":"37i9dQZF1DWYok9l1JL7GM","n":20,"a":1604116860000,"p":193}],"pp":193},"400590":{"i":"45R6DmpsaoqLujIn6qPTPH","is":"USWB10400590","n":"Wait","a":[{"i":"6eeYhqOX2cpsiHY6gVuvPA","n":"Earshot"}],"p":58,"r":"2004-06-22","l":"Warner Records","im":"https://i.scdn.co/image/ab67616d0000b273fc166a861d377e7e7397485c","ps":[{"i":"37i9dQZF1DXcfZ6moR6J0G","n":48,"a":1601999405000,"p":579}],"pp":579},"401213":{"i":"0RZXNlGPvfMo54fd6uCvAT","is":"USWB10401213","n":"Knuck If You Buck (feat. Lil' Scrappy)","a":[{"i":"5A7d4sfe5ZY1RRf90zlUeo","n":"Crime Mob"},{"i":"5einkgXXrjhfYCyac1FANB","n":"Lil Scrappy"}],"p":60,"r":"2004-07-13","l":"Warner Records","im":"https://i.scdn.co/image/ab67616d0000b273ce782a6af8a03f968a8bf8c5","ps":[{"i":"37i9dQZF1DWYok9l1JL7GM","n":2,"a":1604116860000,"p":231},{"i":"37i9dQZF1DX7DCJxqVk5NA","n":49,"a":1602695301000,"p":34}],"pp":265},"401741":{"i":"0Z7O8GMQShj9TJrm2yX1R6","is":"USWB10401741","n":"Jump - 2004 Remaster","a":[{"i":"2cnMpRsOVqtPMfq7YiFE6K","n":"Van Halen"}],"p":59,"r":"2004","l":"Rhino/Warner Records","im":"https://i.scdn.co/image/ab67616d0000b273c55701722ddba5ee3663ab3d","ps":[{"i":"37i9dQZF1DX4JTjLTaIQbE","n":33,"a":1604402479000,"p":191}],"pp":191},"401771":{"i":"7kWeSMXLxUHHOkFxsS0vhP","is":"USWB10401771","n":"Some Beach","a":[{"i":"1UTPBmNbXNTittyMJrNkvw","n":"Blake Shelton"}],"p":61,"r":"2004-10-26","l":"Warner Records/Nashville","im":"https://i.scdn.co/image/ab67616d0000b273d676ab41a5cfb441ac8e26ce","ps":[{"i":"37i9dQZF1DXcSzYlwgjiSi","n":6,"a":1602082582000,"p":228},{"i":"37i9dQZF1DXdxUH6sNtcDe","n":107,"a":1602337999000,"p":132}],"pp":360},"401857":{"i":"6zJms3MX11Qu1IKF44LoRW","is":"USWB10401857","n":"Us","a":[{"i":"3z6Gk257P9jNcZbBXJNX5i","n":"Regina Spektor"}],"p":53,"r":"2004-08-17","l":"Sire/Warner Records","im":"https://i.scdn.co/image/ab67616d0000b27376fefb2bcf96e221ce6d4508","ps":[{"i":"37i9dQZF1DX4Jyx1uIhxnP","n":16,"a":1602258074000,"p":47}],"pp":47},"401947":{"i":"0Xxww5aUyamJlEm8GkP21i","is":"USWB10401947","n":"Scar","a":[{"i":"6aP8ry8w3bSNyfyqhE8rGf","n":"Missy Higgins"}],"p":60,"r":"2004-01-01","l":"Universal Music Australia Pty. Ltd.","im":"https://i.scdn.co/image/ab67616d0000b273d1012e47b1270d2c81e38cf2","ps":[{"i":"37i9dQZF1DWZTlcGPMirK8","n":68,"a":1602797030000,"p":109},{"i":"37i9dQZF1DWXd7abuqiatD","n":57,"a":1602738438000,"p":78}],"pp":187},"401971":{"i":"0mUyMawtxj1CJ76kn9gIZK","is":"USWB10401971","n":"Bad Day","a":[{"i":"7xTcuBOIAAIGDOSvwYFPzk","n":"Daniel Powter"}],"p":77,"r":"2005-02-22","l":"Warner Records","im":"https://i.scdn.co/image/ab67616d0000b273d5d74dc15f88ec6e02c7378d","ps":[{"i":"37i9dQZF1DX1Mj6nQRkc5p","n":37,"a":1604296797000,"p":348},{"i":"37i9dQZF1DX5wSQbrOxKS2","n":22,"a":1604098860000,"p":328},{"i":"37i9dQZF1DX0Wwd2q8mZlL","n":41,"a":1601639816000,"p":98},{"i":"37i9dQZF1DX1IsNLQQJRvk","n":81,"a":1605257716000,"p":72},{"i":"37i9dQZF1DX4bw5oBAFpuz","n":92,"a":1602537202000,"p":34},{"i":"37i9dQZF1DX1mDKG3HOIlV","n":10,"a":1604500340000,"p":10},{"i":"37i9dQZF1DX9vEn8vBG5Y1","n":62,"a":1603878629000,"p":7}],"pp":897},"402194":{"i":"24efdUt3KGbZ6wnBLp6j2n","is":"USWB10402194","n":"Beating Heart Baby","a":[{"i":"2cyaobEho8uxhqLxwG7j6i","n":"Head Automatica"}],"p":52,"r":"2004-08-10","l":"Warner Records","im":"https://i.scdn.co/image/ab67616d0000b2736cb6fd8be58a86e6ebca252e","ps":[{"i":"37i9dQZF1DX0wiundViT27","n":64,"a":1597882038000,"p":401}],"pp":401},"402409":{"i":"4lgVbDYZR1VV4gEkIueSiw","is":"USWB10402409","n":"Leaving New York","a":[{"i":"4KWTAlx2RvbpseOGMEmROg","n":"R.E.M."}],"p":52,"r":"2004-01-01","l":"Concord Records","im":"https://i.scdn.co/image/ab67616d0000b2734b1af458f45d3aa0e47d7a30","ps":[{"i":"37i9dQZF1DX5PBX3AOpG5l","n":29,"a":1604505977000,"p":11}],"pp":11},"403356":{"i":"2qt8jR309s3wJsUmUlRhE6","is":"USWB10403356","n":"Crazy - Acoustic","a":[{"i":"5GtMEZEeFFsuHY8ad4kOxv","n":"Seal"}],"p":43,"r":"2004","l":"Warner Records","im":"https://i.scdn.co/image/ab67616d0000b273cf729cd22c1ed5fe53ae65a2","ps":[{"i":"37i9dQZF1DWYGZAMYFDM8S","n":55,"a":1603756734000,"p":212}],"pp":212},"403358":{"i":"3YfiGjwBzBsDrYPqAJsD4z","is":"USWB10403358","n":"Kiss from a Rose - Acoustic","a":[{"i":"5GtMEZEeFFsuHY8ad4kOxv","n":"Seal"}],"p":59,"r":"2004","l":"Warner Records","im":"https://i.scdn.co/image/ab67616d0000b273cf729cd22c1ed5fe53ae65a2","ps":[{"i":"37i9dQZF1DWYGZAMYFDM8S","n":62,"a":1603756734000,"p":198}],"pp":198},"403433":{"i":"0AXZ0NEEylEhBda574NrmG","is":"USWB10403433","n":"Swimming Song","a":[{"i":"7krh6ZjG7i7jvLGiG3YNJF","n":"Kate & Anna McGarrigle"}],"p":40,"r":"1975","l":"Rhino/Warner Records","im":"https://i.scdn.co/image/ab67616d0000b27371c08a3db39ea86a771ec487","ps":[{"i":"37i9dQZF1DWVmps5U8gHNv","n":65,"a":1602093761000,"p":357}],"pp":357},"403621":{"i":"7ssWIely07EPJyU028jZZq","is":"USWB10403621","n":"Just a Kid","a":[{"i":"2QoU3awHVdcHS8LrZEKvSM","n":"Wilco"}],"p":31,"r":"2004-11-09","l":"Sire","im":"https://i.scdn.co/image/ab67616d0000b27337dcc623f72b6d492f56f675","ps":[{"i":"37i9dQZF1DWWsq4e0rDzty","n":42,"a":1601399863000,"p":44}],"pp":44},"403681":{"i":"5sNESr6pQfIhL3krM8CtZn","is":"USWB10403681","n":"Numb / Encore","a":[{"i":"3nFkdlSjzX9mRTtwJOzDYB","n":"JAY-Z"},{"i":"6XyY86QOPPrYVGvF9ch6wz","n":"Linkin Park"}],"p":76,"r":"2004-11-30","l":"Warner Records/Roc-A-Fella","im":"https://i.scdn.co/image/ab67616d0000b2737282412ad025c14f7039f516","ps":[{"i":"37i9dQZF1DX1mDKG3HOIlV","n":42,"a":1604500340000,"p":7}],"pp":7},"404010":{"i":"46uAPYj07jhrHt0ggMiwtA","is":"USWB10404010","n":"Iris - Live","a":[{"i":"2sil8z5kiy4r76CRTXxBCA","n":"The Goo Goo Dolls"}],"p":46,"r":"2004-11-23","l":"Warner Records","im":"https://i.scdn.co/image/ab67616d0000b2731853fac9a1eae995032ea2a5","ps":[{"i":"37i9dQZF1DX5Oee8FxGUG9","n":99,"a":1592551800000,"p":39}],"pp":39},"405029":{"i":"5ezYm2LkW25YhkkTp7bC9u","is":"USWB10405029","n":"You're Gonna Need Me","a":[{"i":"2JSjCHK79gdaiPWdKiNUNp","n":"Dionne Warwick"}],"p":44,"r":"1973","l":"Rhino","im":"https://i.scdn.co/image/ab67616d0000b273155cddf42ec13794f057a83c","ps":[{"i":"37i9dQZF1DWX2Y4jtvVshZ","n":49,"a":1605279585000,"p":125}],"pp":125},"500047":{"i":"3YsG8BwqrJzM3DOqYpFLp0","is":"USWB10500047","n":"Leafy Incline","a":[{"i":"2mncWLPUUFpNvBLkHzTsDO","n":"Tad"}],"p":44,"r":"1993","l":"Rhino/Warner Records","im":"https://i.scdn.co/image/ab67616d0000b273df7dc7c2e98cf0432466624a","ps":[{"i":"37i9dQZF1DX11ghcIxjcjE","n":45,"a":1602167671000,"p":583}],"pp":583},"500077":{"i":"0VriklsiNGvHpyP3uwWuD7","is":"USWB10500077","n":"Stupid Like This","a":[{"i":"7xTcuBOIAAIGDOSvwYFPzk","n":"Daniel Powter"}],"p":33,"r":"2020-07-17","l":"Warner Music Group - X5 Music Group","im":"https://i.scdn.co/image/ab67616d0000b2730c532dba85181e4ffb69c51c","ps":[{"i":"37i9dQZF1DWTZN2MMN712S","n":32,"a":1604975700000,"p":142}],"pp":142},"501550":{"i":"2iQvYaOlUcuVgczMtRvAcV","is":"USWB10501550","n":"Damaged Goods - Remastered","a":[{"i":"3AmWjMXXtBJOmNGpUFSOAl","n":"Gang Of Four"}],"p":0,"r":"1979","l":"Rhino/Warner Bros.","im":"https://i.scdn.co/image/ab67616d0000b273c6e6b7908a1c6b6bb47efa94","ps":[{"i":"37i9dQZF1DXdTCdwCKzXwo","n":19,"a":1544804078000,"p":676}],"pp":676},"501912":{"i":"3sHH7lklbfpcraDDvYnjo7","is":"USWB10501912","n":"Bat Country","a":[{"i":"0nmQIMXWTXfhgOBdNzhGOs","n":"Avenged Sevenfold"}],"p":69,"r":"2005-06-06","l":"Warner Records","im":"https://i.scdn.co/image/ab67616d0000b27364312d8b81af58876a7ca5ee","ps":[{"i":"37i9dQZF1DX5OUjSS1OMgV","n":86,"a":1598462981000,"p":301},{"i":"37i9dQZF1DWXNFSTtym834","n":55,"a":1603806854000,"p":270}],"pp":571},"502129":{"i":"13M7BEAZErxrA5k46pXnae","is":"USWB10502129","n":"Give Me the Night","a":[{"i":"1twC2fwPG5FkvYcMpVBQRz","n":"Randy Crawford"}],"p":29,"r":"2017-06-20","l":"Warner Music Group - X5 Music Group","im":"https://i.scdn.co/image/ab67616d0000b273afffefc2c74752a018dbb291","ps":[{"i":"37i9dQZF1DWX2Y4jtvVshZ","n":131,"a":1605279585000,"p":55}],"pp":55},"502457":{"i":"6ndmKwWqMozN2tcZqzCX4K","is":"USWB10502457","n":"Remember the Name (feat. Styles of Beyond)","a":[{"i":"7dWYWUbO68rXJOcyA7SpJk","n":"Fort Minor"},{"i":"5bf6yYgHODBW5EreBZshpX","n":"Styles Of Beyond"}],"p":74,"r":"2005-11-21","l":"Machine Shop/Warner Records","im":"https://i.scdn.co/image/ab67616d0000b273063fc4921a6d7fbac76e9bba","ps":[{"i":"37i9dQZF1DWVGdX9MUCxQC","n":42,"a":1605167352000,"p":43},{"i":"37i9dQZF1DX1mDKG3HOIlV","n":86,"a":1604500340000,"p":5}],"pp":48},"502512":{"i":"0ll2bQyOTzAPPBKqp6FFcp","is":"USWB10502512","n":"Psycho Killer - Acoustic Version","a":[{"i":"2x9SpqnPi8rlE9pjHBwmSC","n":"Talking Heads"}],"p":0,"r":"2018-06-27","l":"X5 Music Group","im":"https://i.scdn.co/image/ab67616d0000b2734d1d48499319bdf40fc67ab9","ps":[{"i":"37i9dQZF1DX3xuDGW6ByRP","n":41,"a":1601607780000,"p":112}],"pp":112},"502659":{"i":"4ECvB9frSDegHfKNRh9dwT","is":"USWB10502659","n":"4ever","a":[{"i":"1dIdBZaaHRW2bDTkHNfWln","n":"The Veronicas"}],"p":56,"r":"2005-10-18","l":"Sire/Warner Records","im":"https://i.scdn.co/image/ab67616d0000b273dd5ead55bbde87d6f73b86ef","ps":[{"i":"37i9dQZF1DWXd7abuqiatD","n":38,"a":1602738438000,"p":94}],"pp":94},"502841":{"i":"2zdlkG9g5Mt0alUdqn7s3D","is":"USWB10502841","n":"I Zimbra - 2005 Remaster","a":[{"i":"2x9SpqnPi8rlE9pjHBwmSC","n":"Talking Heads"}],"p":44,"r":"1979-08-03","l":"Rhino/Warner Records","im":"https://i.scdn.co/image/ab67616d0000b2738365f74aa622b1b86962c8dd","ps":[{"i":"37i9dQZF1DWTz2CbxASWRu","n":186,"a":1605193244000,"p":57}],"pp":57},"502860":{"i":"1i6N76fftMZhijOzFQ5ZtL","is":"USWB10502860","n":"Psycho Killer - 2005 Remaster","a":[{"i":"2x9SpqnPi8rlE9pjHBwmSC","n":"Talking Heads"}],"p":75,"r":"1977-09-16","l":"Rhino/Warner Records","im":"https://i.scdn.co/image/ab67616d0000b2733711fa074510441f17c0d594","ps":[{"i":"37i9dQZF1DXdTCdwCKzXwo","n":6,"a":1544804078000,"p":770},{"i":"37i9dQZF1DX3z5yKRkYm4P","n":18,"a":1603235738000,"p":134},{"i":"37i9dQZF1DX8fFFusFo0MK","n":47,"a":1603969270000,"p":126},{"i":"37i9dQZF1DWZEa9Yw06mQB","n":123,"a":1603422871000,"p":23}],"pp":1053},"502869":{"i":"38Ngied9rBORlAbLYNCl4k","is":"USWB10502869","n":"Once in a Lifetime - 2005 Remaster","a":[{"i":"2x9SpqnPi8rlE9pjHBwmSC","n":"Talking Heads"}],"p":71,"r":"1980-10-08","l":"Rhino/Warner Records","im":"https://i.scdn.co/image/ab67616d0000b273e56fa8c916dc6ce419dcf557","ps":[{"i":"37i9dQZF1DWY5Exaf30Ns0","n":68,"a":1604901720000,"p":437},{"i":"37i9dQZF1DX0hWmn8d5pRe","n":53,"a":1605262260000,"p":422},{"i":"6YDckiQHBPbMvpcNWsWLRk","n":58,"a":1572870043000,"p":44},{"i":"37i9dQZF1DWVyasWqYs9Zi","n":85,"a":1603822449000,"p":20}],"pp":923},"502911":{"i":"6aBUnkXuCEQQHAlTokv9or","is":"USWB10502911","n":"This Must Be the Place (Naive Melody) - 2005 Remaster","a":[{"i":"2x9SpqnPi8rlE9pjHBwmSC","n":"Talking Heads"}],"p":72,"r":"1983-05-31","l":"Rhino/Warner Records","im":"https://i.scdn.co/image/ab67616d0000b273e35e2e2a4bfa8a30a78fc532","ps":[{"i":"37i9dQZF1DXdX26YqusBdd","n":58,"a":1605303850000,"p":168},{"i":"37i9dQZF1DXe87nR6LypeT","n":6,"a":1603980897000,"p":23}],"pp":191},"503444":{"i":"4503U9TuPbVDz6TlKS0Z1a","is":"USWB10503444","n":"Wings of a Butterfly","a":[{"i":"74aLweE8FHHf4yN5TWv1GM","n":"HIM"}],"p":43,"r":"2005","l":"WM Finland","im":"https://i.scdn.co/image/ab67616d0000b2736a3672a20abd7dbf9d5edfc0","ps":[{"i":"37i9dQZF1DX1BGjOuHbaDS","n":53,"a":1602074566000,"p":110},{"i":"37i9dQZF1DWTREX34Zufzd","n":83,"a":1605208219000,"p":69}],"pp":179},"504319":{"i":"3850dYVgOFIXJh5U4BFEWH","is":"USWB10504319","n":"Hung Up","a":[{"i":"6tbjWDEIzxoDsBA1FuhfPW","n":"Madonna"}],"p":73,"r":"2005-11-11","l":"Warner Records","im":"https://i.scdn.co/image/ab67616d0000b273efcbc3f42da96cea7583bb6f","ps":[{"i":"37i9dQZF1DX9T4s8vww3Eu","n":57,"a":1605195446000,"p":26}],"pp":26},"504642":{"i":"1Lg9aMPCykp6LybqcVCXiO","is":"USWB10504642","n":"Hung Up - Radio Version","a":[{"i":"6tbjWDEIzxoDsBA1FuhfPW","n":"Madonna"}],"p":52,"r":"2005-11-04","l":"Warner Records/Maverick","im":"https://i.scdn.co/image/ab67616d0000b273f194a6c8e0456ca5e347bb1d","ps":[{"i":"37i9dQZF1DWXeOurMWUII5","n":48,"a":1605261178000,"p":422}],"pp":422},"504973":{"i":"1AQQ9DdpEemMVTHNz4eG9a","is":"USWB10504973","n":"Get Together","a":[{"i":"6tbjWDEIzxoDsBA1FuhfPW","n":"Madonna"}],"p":55,"r":"2005-11-11","l":"Warner Records","im":"https://i.scdn.co/image/ab67616d0000b273efcbc3f42da96cea7583bb6f","ps":[{"i":"37i9dQZF1DWUSO9kvC46mW","n":34,"a":1604568214000,"p":9}],"pp":9},"504974":{"i":"55whbebR4olz2HHcRQa2kx","is":"USWB10504974","n":"Sorry","a":[{"i":"6tbjWDEIzxoDsBA1FuhfPW","n":"Madonna"}],"p":60,"r":"2005-11-11","l":"Warner Records","im":"https://i.scdn.co/image/ab67616d0000b273efcbc3f42da96cea7583bb6f","ps":[{"i":"37i9dQZF1DWUSO9kvC46mW","n":6,"a":1604568214000,"p":13}],"pp":13},"504979":{"i":"5hmRhU6fWzH0NjYmfhHjhp","is":"USWB10504979","n":"Jump","a":[{"i":"6tbjWDEIzxoDsBA1FuhfPW","n":"Madonna"}],"p":57,"r":"2005-11-11","l":"Warner Records","im":"https://i.scdn.co/image/ab67616d0000b273efcbc3f42da96cea7583bb6f","ps":[{"i":"37i9dQZF1DWUSO9kvC46mW","n":17,"a":1604568214000,"p":11}],"pp":11},"505222":{"i":"70YvYr2hGlS01bKRIho1HM","is":"USWB10505222","n":"La Grange - 2005 Remaster","a":[{"i":"2AM4ilv6UzW0uMRuqKtDgN","n":"ZZ Top"}],"p":76,"r":"1973-07-26","l":"Rhino/Warner Records","im":"https://i.scdn.co/image/ab67616d0000b2730fe2ec86a0ec561ef2e2aae1","ps":[{"i":"37i9dQZF1DWTJ7xPn4vNaz","n":63,"a":1597672531000,"p":1060},{"i":"37i9dQZF1DWXTHBOfJ8aI7","n":9,"a":1604576249000,"p":542},{"i":"37i9dQZF1DX7LGssahBoms","n":21,"a":1602888780000,"p":295},{"i":"37i9dQZF1DX1BGjOuHbaDS","n":9,"a":1602074566000,"p":172},{"i":"37i9dQZF1DX6tTgVVjGVN7","n":13,"a":1603487760000,"p":104}],"pp":2173},"505295":{"i":"7c1iI6dwdCpHGYT8DGEfab","is":"USWB10505295","n":"Uninvited","a":[{"i":"6ogn9necmbUdCppmNnGOdi","n":"Alanis Morissette"}],"p":58,"r":"2005-11-11","l":"Maverick","im":"https://i.scdn.co/image/ab67616d0000b273d00e49003543a5bb5aa5b873","ps":[{"i":"37i9dQZF1DX7EMLexEFdeT","n":17,"a":1604030520000,"p":123}],"pp":123},"600454":{"i":"2mlIzqDE7RaMaMx1UPdsXL","is":"USWB10600454","n":"The Yeah Yeah Yeah Song","a":[{"i":"16eRpMNXSQ15wuJoeqguaB","n":"The Flaming Lips"}],"p":45,"r":"2006-04-03","l":"Warner Records","im":"https://i.scdn.co/image/ab67616d0000b27363c440679eeb0975f217e1c7","ps":[{"i":"37i9dQZF1DX0YKekzl0blG","n":68,"a":1545231521000,"p":357}],"pp":357},"600586":{"i":"6fx1fKIs5e0pBL5FpdC7RB","is":"USWB10600586","n":"MakeDamnSure","a":[{"i":"24XtlMhEMNdi822vi0MhY1","n":"Taking Back Sunday"}],"p":67,"r":"2006-04-25","l":"Craft Recordings","im":"https://i.scdn.co/image/ab67616d0000b27395fe4146184ee807c884326b","ps":[{"i":"37i9dQZF1DX4TGLEwxideE","n":6,"a":1604030460000,"p":27}],"pp":27},"600587":{"i":"6GskIhdM6TN6EkPgeSjVfW","is":"USWB10600587","n":"Fidelity","a":[{"i":"3z6Gk257P9jNcZbBXJNX5i","n":"Regina Spektor"}],"p":53,"r":"2006-06-13","l":"Sire","im":"https://i.scdn.co/image/ab67616d0000b2737fd2d3669c086850c0f766e8","ps":[{"i":"37i9dQZF1DWTwnEm1IYyoj","n":180,"a":1603479720000,"p":351}],"pp":351},"600700":{"i":"10Nmj3JCNoMeBQ87uw5j8k","is":"USWB10600700","n":"Dani California","a":[{"i":"0L8ExT028jH3ddEcZwqJJ5","n":"Red Hot Chili Peppers"}],"p":77,"r":"2006-05-09","l":"Warner Records","im":"https://i.scdn.co/image/ab67616d0000b27309fd83d32aee93dceba78517","ps":[{"i":"37i9dQZF1DX6ALfRKlHn1t","n":112,"a":1595540709000,"p":296},{"i":"37i9dQZF1DX3zHI0Yn6qtf","n":59,"a":1604664532000,"p":73},{"i":"37i9dQZF1DWUSO9kvC46mW","n":16,"a":1604568214000,"p":11}],"pp":380},"600738":{"i":"0x5xRTV6l8tCr8ShASj9Wd","is":"USWB10600738","n":"The Dance of the Witches","a":[{"i":"3dRfiJ2650SZu6GbydcHNb","n":"John Williams"}],"p":35,"r":"1986","l":"Rhino/Warner Records","im":"https://i.scdn.co/image/ab67616d0000b27365f80b0139a2b4e6eabfa91a","ps":[{"i":"37i9dQZF1DXafCT9DHTijq","n":33,"a":1603263699000,"p":182}],"pp":182},"601591":{"i":"2aibwv5hGXSgw7Yru8IYTO","is":"USWB10601591","n":"Snow (Hey Oh)","a":[{"i":"0L8ExT028jH3ddEcZwqJJ5","n":"Red Hot Chili Peppers"}],"p":79,"r":"2006-05-09","l":"Warner Records","im":"https://i.scdn.co/image/ab67616d0000b27309fd83d32aee93dceba78517","ps":[{"i":"37i9dQZF1DWUF3bcja4I8P","n":0,"a":1602685542000,"p":448},{"i":"37i9dQZF1DX5wSQbrOxKS2","n":9,"a":1604098860000,"p":374},{"i":"37i9dQZF1DXacPj7eARo6k","n":59,"a":1602143066000,"p":334},{"i":"37i9dQZF1DX9qUVnHy7VXV","n":6,"a":1605337620000,"p":318},{"i":"37i9dQZF1DXdHKb3VkLtuj","n":54,"a":1603130622000,"p":187},{"i":"37i9dQZF1DX9xdWyDn7XX8","n":12,"a":1604005534000,"p":65},{"i":"37i9dQZF1DWTIlGSTRox0A","n":94,"a":1604500318000,"p":5}],"pp":1731},"601621":{"i":"2bbhyUWJ5VjdfI3P4PRLu2","is":"USWB10601621","n":"Samson","a":[{"i":"3z6Gk257P9jNcZbBXJNX5i","n":"Regina Spektor"}],"p":51,"r":"2006-06-13","l":"Sire","im":"https://i.scdn.co/image/ab67616d0000b2737fd2d3669c086850c0f766e8","ps":[{"i":"37i9dQZF1DWUw3COUvHCkS","n":5,"a":1603722034000,"p":168}],"pp":168},"602450":{"i":"71V89tJj9CboDyzncO6ZN2","is":"USWB10602450","n":"Stars Are Blind","a":[{"i":"1vkJFCwstOoJO7yQ4lTtLK","n":"Paris Hilton"}],"p":56,"r":"2006-08-14","l":"Warner Records","im":"https://i.scdn.co/image/ab67616d0000b273442533891bd8dc4c1ce79049","ps":[{"i":"37i9dQZF1DWUSO9kvC46mW","n":43,"a":1604568214000,"p":9}],"pp":9},"603362":{"i":"5OqpBsJQ45wuPJSDORXgkX","is":"USWB10603362","n":"Bird Dog (Single Version)","a":[{"i":"4ACplpEqD6JIVgKrafauzs","n":"The Everly Brothers"}],"p":27,"r":"2019-07-12","l":"Warner Music Group - X5 Music Group","im":"https://i.scdn.co/image/ab67616d0000b2734934c9839ae3bb7494821f75","ps":[{"i":"37i9dQZF1DWUB167twpvS4","n":8,"a":1602437706000,"p":64}],"pp":64},"604718":{"i":"4a8mshDjwAIwNcgDvCtMMa","is":"USWB10604718","n":"Ain't Nothing Wrong with That","a":[{"i":"4xac3zhHlBm5QDxbZeqgeR","n":"Robert Randolph & The Family Band"}],"p":43,"r":"2006-09-25","l":"Warner Records","im":"https://i.scdn.co/image/ab67616d0000b273fa7859c228684843c9d8a55e","ps":[{"i":"37i9dQZF1DWSKpvyAAcaNZ","n":131,"a":1605279857000,"p":186}],"pp":186},"605992":{"i":"1UEKaf3j6eXeNbySz761lc","is":"USWB10605992","n":"Take It Easy - 2006 Remaster","a":[{"i":"2M4Yt7oKGoYd0wqU44k4i2","n":"Travis Tritt"}],"p":62,"r":"2007-01-30","l":"Rhino/Warner Records","im":"https://i.scdn.co/image/ab67616d0000b273b9f2c30e6363a752a93efa16","ps":[{"i":"37i9dQZF1DWVpjAJGB70vU","n":35,"a":1605192080000,"p":635}],"pp":635},"700721":{"i":"18lR4BzEs7e3qzc0KVkTpU","is":"USWB10700721","n":"What I've Done","a":[{"i":"6XyY86QOPPrYVGvF9ch6wz","n":"Linkin Park"}],"p":77,"r":"2007-05-14","l":"Warner Records","im":"https://i.scdn.co/image/ab67616d0000b27346e207de66ba06422897f769","ps":[{"i":"37i9dQZF1DWTIlGSTRox0A","n":83,"a":1604500318000,"p":5}],"pp":5},"701180":{"i":"5V81mY8qT0LlqOq7W7hxEr","is":"USWB10701180","n":"Goodbye Philadelphia","a":[{"i":"1PjKnsWzJra4dV8OXiNC5F","n":"Peter Cincotti"}],"p":43,"r":"2007-09-04","l":"Warner Records","im":"https://i.scdn.co/image/ab67616d0000b2739347fb04b7b922eb218787ec","ps":[{"i":"37i9dQZF1DXacPj7eARo6k","n":89,"a":1602143066000,"p":247}],"pp":247},"701212":{"i":"58AS4weYlUWvGztZbKIuAU","is":"USWB10701212","n":"Leave Out All The Rest","a":[{"i":"6XyY86QOPPrYVGvF9ch6wz","n":"Linkin Park"}],"p":55,"r":"2007-05-14","l":"Warner Records","im":"https://i.scdn.co/image/ab67616d0000b2737144af5790b8937dee6b7f42","ps":[{"i":"37i9dQZF1DX2UXfvEIZvDK","n":45,"a":1603808183000,"p":412}],"pp":412},"701213":{"i":"78gsvivelCP8Kh0tSRTy8D","is":"USWB10701213","n":"Bleed It Out","a":[{"i":"6XyY86QOPPrYVGvF9ch6wz","n":"Linkin Park"}],"p":56,"r":"2007-05-14","l":"Warner Records","im":"https://i.scdn.co/image/ab67616d0000b2737144af5790b8937dee6b7f42","ps":[{"i":"37i9dQZF1DWZUTt0fNaCPB","n":69,"a":1605262318000,"p":417}],"pp":417},"701214":{"i":"0OYcEfskah1egYHjYRvbg1","is":"USWB10701214","n":"Shadow of the Day","a":[{"i":"6XyY86QOPPrYVGvF9ch6wz","n":"Linkin Park"}],"p":67,"r":"2007-05-14","l":"Warner Records","im":"https://i.scdn.co/image/ab67616d0000b27346e207de66ba06422897f769","ps":[{"i":"37i9dQZF1DX0w6SRvtNXby","n":20,"a":1603285260000,"p":178}],"pp":178},"701395":{"i":"09QZAEmdbq28OaNyqTOEvY","is":"USWB10701395","n":"Icky Thump","a":[{"i":"4F84IBURUo98rz4r61KF70","n":"The White Stripes"}],"p":47,"r":"2007-06-15","l":"Warner Records","im":"https://i.scdn.co/image/ab67616d0000b2733bc42fa2921359fa68fddc9a","ps":[{"i":"37i9dQZF1DX1tyCD9QhIWF","n":37,"a":1604323274000,"p":945},{"i":"37i9dQZF1DWY6vTWIdZ54A","n":109,"a":1596244244000,"p":198},{"i":"37i9dQZF1DX1helbHcrYM1","n":31,"a":1603014868000,"p":124}],"pp":1267},"701734":{"i":"4b0XF7CDpJEBAdVHMw7amV","is":"USWB10701734","n":"Just Got Started Lovin' You","a":[{"i":"3VStI6m5Ig9FAyUaa0lYAP","n":"James Otto"}],"p":59,"r":"2008-04-07","l":"Warner Records","im":"https://i.scdn.co/image/ab67616d0000b273eeb4940c2a5c2f74f3cb0c98","ps":[{"i":"37i9dQZF1DXdxUH6sNtcDe","n":130,"a":1602337999000,"p":105}],"pp":105},"702680":{"i":"0OBwxFLu6Yj61s2OagYbgY","is":"USWB10702680","n":"Gimme All Your Lovin'","a":[{"i":"2AM4ilv6UzW0uMRuqKtDgN","n":"ZZ Top"}],"p":70,"r":"1983-03-23","l":"Rhino/Warner Records","im":"https://i.scdn.co/image/ab67616d0000b27328a00032ff3b86af3d7e0e54","ps":[{"i":"37i9dQZF1DX4vth7idTQch","n":9,"a":1601561160000,"p":668},{"i":"37i9dQZF1DWZqt2ERoYVIt","n":37,"a":1604606645000,"p":23}],"pp":691},"702682":{"i":"1UBQ5GK8JaQjm5VbkBZY66","is":"USWB10702682","n":"Sharp Dressed Man - 2008 Remaster","a":[{"i":"2AM4ilv6UzW0uMRuqKtDgN","n":"ZZ Top"}],"p":73,"r":"1983-03-23","l":"Rhino/Warner Records","im":"https://i.scdn.co/image/ab67616d0000b27328a00032ff3b86af3d7e0e54","ps":[{"i":"37i9dQZF1DX68H8ZujdnN7","n":87,"a":1602166797000,"p":511}],"pp":511},"703324":{"i":"12KsTSPgKRxekOejhNzmDZ","is":"USWB10703324","n":"Whistle Bump","a":[{"i":"0hE3uA2w3guHeKvuc7BpRr","n":"Deodato"}],"p":31,"r":"2018-02-16","l":"Warner Music Group - X5 Music Group","im":"https://i.scdn.co/image/ab67616d0000b2739b7671eab1fe2319ab8ab78a","ps":[{"i":"37i9dQZF1DX8f5qTGj8FYl","n":63,"a":1605243720000,"p":245},{"i":"37i9dQZF1DWXeJvz3fBL9K","n":10,"a":1601639936000,"p":66}],"pp":311},"703342":{"i":"3ZkG1IBv31CsqLOHyreNZU","is":"USWB10703342","n":"Keep On Movin'","a":[{"i":"0hE3uA2w3guHeKvuc7BpRr","n":"Deodato"}],"p":32,"r":"2020-02-14","l":"Warner Music Group - X5 Music Group","im":"https://i.scdn.co/image/ab67616d0000b273911473018a07fe1b45f392c6","ps":[{"i":"37i9dQZF1DWXncK9DGeLh7","n":43,"a":1603287481000,"p":279}],"pp":279},"704278":{"i":"0TxXEbxn52XsuAhxb6VFZw","is":"USWB10704278","n":"This Kiss","a":[{"i":"25NQNriVT2YbSW80ILRWJa","n":"Faith Hill"}],"p":63,"r":"2007","l":"Warner Records/Nashville","im":"https://i.scdn.co/image/ab67616d0000b2733ee43d5dbf7da3e65be844b3","ps":[{"i":"37i9dQZF1DWXVBw4Z7cIDC","n":12,"a":1604665086000,"p":219}],"pp":219},"704285":{"i":"6gQZKkphKIMxZgca5r7ImA","is":"USWB10704285","n":"Express Yourself - Remastered Version","a":[{"i":"2t0kaaDtGZtmpczIAMaVTQ","n":"Charles Wright & The Watts 103rd Street Rhythm Band"}],"p":51,"r":"2007-10-22","l":"Rhino/Warner Records","im":"https://i.scdn.co/image/ab67616d0000b2736887b9c37f901387f65e1271","ps":[{"i":"37i9dQZF1DWX2Y4jtvVshZ","n":163,"a":1605279585000,"p":40}],"pp":40},"704602":{"i":"40bm28QcJT5My540ymSQ2y","is":"USWB10704602","n":"Untouched","a":[{"i":"1dIdBZaaHRW2bDTkHNfWln","n":"The Veronicas"}],"p":58,"r":"2005","l":"Sire","im":"https://i.scdn.co/image/ab67616d0000b2731076b9a7372da9c95dd51008","ps":[{"i":"37i9dQZF1DWXd7abuqiatD","n":45,"a":1602738438000,"p":88},{"i":"37i9dQZF1DX56hj7oNZ6Lh","n":8,"a":1604500301000,"p":13}],"pp":101},"704606":{"i":"7MFvqBJ3ozTwDrf5VfoW8U","is":"USWB10704606","n":"Take Me on the Floor","a":[{"i":"1dIdBZaaHRW2bDTkHNfWln","n":"The Veronicas"}],"p":45,"r":"2007-10-30","l":"Sire/Warner Records","im":"https://i.scdn.co/image/ab67616d0000b2730f3819fd1601ca0421194d32","ps":[{"i":"37i9dQZF1DWZTlcGPMirK8","n":6,"a":1602797030000,"p":203}],"pp":203},"704697":{"i":"0eG5CqXwJpa5MBjYyg1lRm","is":"USWB10704697","n":"Slide","a":[{"i":"2sil8z5kiy4r76CRTXxBCA","n":"The Goo Goo Dolls"}],"p":55,"r":"2007-11-06","l":"Warner Records","im":"https://i.scdn.co/image/ab67616d0000b273d54c4b12c9242bda37f4bb25","ps":[{"i":"37i9dQZF1DXcSNirXzsHRX","n":64,"a":1603439699000,"p":114},{"i":"37i9dQZF1DX0Wwd2q8mZlL","n":94,"a":1601639816000,"p":57}],"pp":171},"704707":{"i":"6vrUTGn5p8IrfTZ0J6sIVM","is":"USWB10704707","n":"Iris","a":[{"i":"2sil8z5kiy4r76CRTXxBCA","n":"The Goo Goo Dolls"}],"p":74,"r":"2007-11-06","l":"Warner Records","im":"https://i.scdn.co/image/ab67616d0000b273d54c4b12c9242bda37f4bb25","ps":[{"i":"37i9dQZF1DWZAzKUemdham","n":34,"a":1602154990000,"p":122},{"i":"37i9dQZF1DX0Wwd2q8mZlL","n":73,"a":1601639816000,"p":71},{"i":"37i9dQZF1DWSY75PtDqTkW","n":175,"a":1603793059000,"p":29}],"pp":222}},"s":["9","1","0","8"]}