{"d":{"162":{"i":"0MildYhazb49zK3rtOtD4t","is":"USWD10525162","n":"In Fondo Al Mar - di \"La Sirenetta\"","a":[{"i":"3X9Y3dWCa9EZFAyhFkftF7","n":"Ronny Grant"}],"p":27,"r":"2018-05-25","l":"Walt Disney Records","im":"https://i.scdn.co/image/ab67616d0000b27350cfe83565c6cf7d2ad3f0d2","ps":[{"i":"37i9dQZF1DX91Bj5bGwTUr","n":8,"a":1603374920000,"p":137}],"pp":137},"355":{"i":"784Nv62mQQo6qSgUEIyJje","is":"USWD10525355","n":"Sei Dentro Me - di \"Tarzan\"","a":[{"i":"4lxfqrEsLX6N1N4OCSkILp","n":"Phil Collins"},{"i":"600gRfYqOtqOFBuRCF5SE8","n":"Marisa Luca"}],"p":38,"r":"2018-11-23","l":"Walt Disney Records","im":"https://i.scdn.co/image/ab67616d0000b2730e4fae3731fbdf40b838d88b","ps":[{"i":"37i9dQZF1DX91Bj5bGwTUr","n":57,"a":1603374920000,"p":84}],"pp":84},"357":{"i":"6TLhBQyNuRbrdhCVpRQAFd","is":"USWD10525357","n":"Al di Fuori di Me - di \"Tarzan\"","a":[{"i":"4lxfqrEsLX6N1N4OCSkILp","n":"Phil Collins"}],"p":32,"r":"2018-05-25","l":"Walt Disney Records","im":"https://i.scdn.co/image/ab67616d0000b27350cfe83565c6cf7d2ad3f0d2","ps":[{"i":"37i9dQZF1DX91Bj5bGwTUr","n":22,"a":1603374920000,"p":119}],"pp":119},"402":{"i":"5wLFZj4RZjCWb4ugTQ91DK","is":"USWD10525402","n":"Hai Sentito?/Mi Domando","a":[{"i":"5dE064f6Myv8kofeKJsXGF","n":"Cast of Sleeping Beauty"}],"p":19,"r":"2002-01-01","l":"Walt Disney Records","im":"https://i.scdn.co/image/ab67616d0000b273adc72ed38082b60797084406","ps":[{"i":"37i9dQZF1DX91Bj5bGwTUr","n":81,"a":1603374920000,"p":66}],"pp":66},"469":{"i":"1WTt2xDqIiXadSkKmwjWJV","is":"USWD10525469","n":"君はともだち","a":[{"i":"2Xgqw0qSxzLPXOgPg1NEUL","n":"Diamond Yukai"}],"p":0,"r":"2000-02-23","l":"DISNEY","im":"https://i.scdn.co/image/ab67616d0000b273c9a14322d8a22ff5010ff9a1","ps":[{"i":"37i9dQZF1DX1lolQkPIs5s","n":73,"a":1602788638000,"p":150},{"i":"37i9dQZF1DWX8kJPhC2CQs","n":5,"a":1602141849000,"p":25}],"pp":175},"581":{"i":"1eOkJKTffWqoM7pQmO8gKA","is":"USWD10525581","n":"Can You Feel the Love Tonight - Instrumental","a":[{"i":"0qPfO5FCAsfqK3pgqBSAJR","n":"Fred Mollin"}],"p":49,"r":"2014-01-01","l":"Walt Disney Records","im":"https://i.scdn.co/image/ab67616d0000b2733b23cc624370ff62c1fe2191","ps":[{"i":"37i9dQZF1DX0zmsulfyDdq","n":54,"a":1586379648000,"p":131}],"pp":131},"582":{"i":"3wI9eq7AaOYGnaO3kKoA8o","is":"USWD10525582","n":"It's a Small World - Instrumental","a":[{"i":"0qPfO5FCAsfqK3pgqBSAJR","n":"Fred Mollin"}],"p":45,"r":"2018-06-01","l":"Walt Disney Records","im":"https://i.scdn.co/image/ab67616d0000b273c83c508fd0ed5ec4674a17bb","ps":[{"i":"37i9dQZF1DX0zmsulfyDdq","n":62,"a":1586379648000,"p":121}],"pp":121},"588":{"i":"747WbLmzVVbiNDMx2LL9Ic","is":"USWD10525588","n":"The Bare Necessities - Instrumental","a":[{"i":"0qPfO5FCAsfqK3pgqBSAJR","n":"Fred Mollin"}],"p":44,"r":"2018-06-01","l":"Walt Disney Records","im":"https://i.scdn.co/image/ab67616d0000b273c83c508fd0ed5ec4674a17bb","ps":[{"i":"37i9dQZF1DX0zmsulfyDdq","n":59,"a":1586379648000,"p":124}],"pp":124},"590":{"i":"41xfXGP8qwohCKMIv61DmF","is":"USWD10525590","n":"Lavender Blue (Dilly Dilly) - Instrumental","a":[{"i":"0qPfO5FCAsfqK3pgqBSAJR","n":"Fred Mollin"}],"p":47,"r":"2014-01-01","l":"Walt Disney Records","im":"https://i.scdn.co/image/ab67616d0000b2733b23cc624370ff62c1fe2191","ps":[{"i":"37i9dQZF1DX0zmsulfyDdq","n":56,"a":1586379648000,"p":128}],"pp":128},"596":{"i":"11ivd2hEFCMAQa5a8077Xo","is":"USWD10525596","n":"The Second Star to the Right - Instrumental","a":[{"i":"0qPfO5FCAsfqK3pgqBSAJR","n":"Fred Mollin"}],"p":48,"r":"2014-01-01","l":"Walt Disney Records","im":"https://i.scdn.co/image/ab67616d0000b2733b23cc624370ff62c1fe2191","ps":[{"i":"37i9dQZF1DX0zmsulfyDdq","n":53,"a":1586379648000,"p":132}],"pp":132},"598":{"i":"3hSUUyu64UofrhKKg5zAOQ","is":"USWD10525598","n":"Bibbidi Bobbidi Boo - Instrumental","a":[{"i":"0qPfO5FCAsfqK3pgqBSAJR","n":"Fred Mollin"}],"p":46,"r":"2018-06-01","l":"Walt Disney Records","im":"https://i.scdn.co/image/ab67616d0000b273c83c508fd0ed5ec4674a17bb","ps":[{"i":"37i9dQZF1DX0zmsulfyDdq","n":43,"a":1586379648000,"p":146}],"pp":146},"604":{"i":"62kKo1gIWTfZEyAks2NV7F","is":"USWD10525604","n":"You'll Be In My Heart - Instrumental","a":[{"i":"0qPfO5FCAsfqK3pgqBSAJR","n":"Fred Mollin"}],"p":49,"r":"2014-01-01","l":"Walt Disney Records","im":"https://i.scdn.co/image/ab67616d0000b2733b23cc624370ff62c1fe2191","ps":[{"i":"37i9dQZF1DX0zmsulfyDdq","n":57,"a":1586379648000,"p":127}],"pp":127},"627":{"i":"0bivJjTXYLREZCNOcw2XSQ","is":"USWD10525627","n":"Under the Sea","a":[{"i":"0MTwHcQjpWkqYdHPkA1Ncd","n":"Tsunehiko Kamijyou"}],"p":29,"r":"2003-11-27","l":"Walt Disney Records","im":"https://i.scdn.co/image/ab67616d0000b273a53c18dded35eecd56c849fe","ps":[{"i":"37i9dQZF1DX1lolQkPIs5s","n":89,"a":1602788638000,"p":128}],"pp":128},"680":{"i":"0p4PSzFicC3XHSgz6l5H4m","is":"USWD10525680","n":"Bibbidi-Bobbidi-Bu - di \"Cenerentola\"","a":[{"i":"0H9zPknUQafYLUSiQKL04T","n":"Lydia Simoneschi"}],"p":21,"r":"2018-11-23","l":"Walt Disney Records","im":"https://i.scdn.co/image/ab67616d0000b2730e4fae3731fbdf40b838d88b","ps":[{"i":"37i9dQZF1DX91Bj5bGwTUr","n":79,"a":1603374920000,"p":67}],"pp":67},"681":{"i":"2JnStCpGqMtuyz8X0wBtjf","is":"USWD10525681","n":"Lo Stretto Indispensabile - di \"Il Libro della Giungla\"","a":[{"i":"02SQ26KK9bnOAmuso5MzbB","n":"Tony De Falco"},{"i":"3ZsBz0yNEC9w7AWizSSny8","n":"Luigi Palma"}],"p":23,"r":"2018-05-25","l":"Walt Disney Records","im":"https://i.scdn.co/image/ab67616d0000b27350cfe83565c6cf7d2ad3f0d2","ps":[{"i":"37i9dQZF1DX91Bj5bGwTUr","n":63,"a":1603374920000,"p":79}],"pp":79},"683":{"i":"1I8T4XLRDhZ3f4a5dsfSkc","is":"USWD10525683","n":"Ehi-Ho! - Da \"Biancaneve e i Sette Nani\"/Colonna Sonora Originale","a":[{"i":"3D1BLLnGnv6BuYfOwFvEO1","n":"The Pietro Carapellucci Choir"}],"p":3,"r":"2012-01-01","l":"Walt Disney Records","im":"https://i.scdn.co/image/ab67616d0000b2732b1f4f5df1860acd368e199f","ps":[{"i":"37i9dQZF1DX91Bj5bGwTUr","n":75,"a":1603374920000,"p":70}],"pp":70},"684":{"i":"3xhcNM6tfvjmzVwB7xk0P2","is":"USWD10525684","n":"Romeo's Swing","a":[{"i":"0FxX8MPSZuDH79F6oS7hzT","n":"Cast - Aristocats"}],"p":34,"r":"2003-01-01","l":"EMI Gold","im":"https://i.scdn.co/image/ab67616d0000b27351f66570565bfcee6f28b0c0","ps":[{"i":"37i9dQZF1DX91Bj5bGwTUr","n":21,"a":1603374920000,"p":120}],"pp":120},"685":{"i":"6RITYuK7kFUjJctBW7zfzo","is":"USWD10525685","n":"Supercalifragilistic-espiralidoso - di \"Mary Poppins\"","a":[{"i":"2XhJbWNi4nMLzlwGai5oB0","n":"Oreste Lionello"},{"i":"427KWxskrxGX8MS5MWj5e9","n":"Tina Centi"}],"p":22,"r":"2018-11-23","l":"Walt Disney Records","im":"https://i.scdn.co/image/ab67616d0000b2730e4fae3731fbdf40b838d88b","ps":[{"i":"37i9dQZF1DX91Bj5bGwTUr","n":67,"a":1603374920000,"p":76}],"pp":76},"687":{"i":"3EhH8YV4uDiFIOsIw3AvRO","is":"USWD10525687","n":"Un Poco Di Zucchero","a":[{"i":"427KWxskrxGX8MS5MWj5e9","n":"Tina Centi"}],"p":31,"r":"2012-01-01","l":"Walt Disney Records","im":"https://i.scdn.co/image/ab67616d0000b273d886a4d2788aacd7cf5de059","ps":[{"i":"37i9dQZF1DX91Bj5bGwTUr","n":45,"a":1603374920000,"p":94}],"pp":94},"690":{"i":"6TdSLtETRkbncwoglZahsm","is":"USWD10525690","n":"Impara a Fischiettar","a":[{"i":"3J6Hmp9Vv89QYsCrIeaVrO","n":"Gianna Spagnulo"}],"p":24,"r":"2012-01-01","l":"Walt Disney Records","im":"https://i.scdn.co/image/ab67616d0000b273d886a4d2788aacd7cf5de059","ps":[{"i":"37i9dQZF1DX91Bj5bGwTUr","n":70,"a":1603374920000,"p":73}],"pp":73},"691":{"i":"6wl6p2ZkAUhJYySGLcDEfx","is":"USWD10525691","n":"Voglio Essere Come Te - di \"Il Libro della Giungla\"/Colonna Sonora Originale","a":[{"i":"02SQ26KK9bnOAmuso5MzbB","n":"Tony De Falco"},{"i":"3ZsBz0yNEC9w7AWizSSny8","n":"Luigi Palma"},{"i":"204aVSeaPVl4jM26zYzJn5","n":"Lorenzo Spadoni"}],"p":5,"r":"2012-01-01","l":"Walt Disney Records","im":"https://i.scdn.co/image/ab67616d0000b27396f2e672cead8fcffa314630","ps":[{"i":"37i9dQZF1DX91Bj5bGwTUr","n":78,"a":1603374920000,"p":68}],"pp":68},"695":{"i":"6gM7vHCCvpedd8ZiiYish7","is":"USWD10525695","n":"Cam-Camini' - di \"Mary Poppins\"","a":[{"i":"2XhJbWNi4nMLzlwGai5oB0","n":"Oreste Lionello"},{"i":"427KWxskrxGX8MS5MWj5e9","n":"Tina Centi"},{"i":"4V1fWv64hzhj94CQWt5zMI","n":"Sandro Acerbo"},{"i":"1dMdZQOtSQVMDNovv7re0X","n":"Liliana Sorrentino"}],"p":21,"r":"2018-05-25","l":"Walt Disney Records","im":"https://i.scdn.co/image/ab67616d0000b27350cfe83565c6cf7d2ad3f0d2","ps":[{"i":"37i9dQZF1DX91Bj5bGwTUr","n":73,"a":1603374920000,"p":71}],"pp":71},"700":{"i":"2tkSJx3tpQdFxj3lh4wIkI","is":"USWD10525700","n":"Urca Urca Tirulero - di \"Robin Hood\"","a":[{"i":"3zmOAgkVZrS9yhg6D4n5GU","n":"Cast of Robin Hood"}],"p":25,"r":"2018-05-25","l":"Walt Disney Records","im":"https://i.scdn.co/image/ab67616d0000b27350cfe83565c6cf7d2ad3f0d2","ps":[{"i":"37i9dQZF1DX91Bj5bGwTUr","n":47,"a":1603374920000,"p":92}],"pp":92},"738":{"i":"0ZzaLKWFHSCgqM7V9TlMXw","is":"USWD10525738","n":"Some Day My Prince Will Come","a":[{"i":"3DFozVvSihC5HdU006Hlx6","n":"YOSHIMI NIIKURA"}],"p":33,"r":"2003-11-27","l":"Walt Disney Records","im":"https://i.scdn.co/image/ab67616d0000b273a53c18dded35eecd56c849fe","ps":[{"i":"37i9dQZF1DX1lolQkPIs5s","n":95,"a":1602788638000,"p":121}],"pp":121},"756":{"i":"4Rwo7ocQ4HA4aJLPuZREmc","is":"USWD10525756","n":"Bella Notte","a":[{"i":"0IKotvQocRLaLRkxROzX9U","n":"Natural Notes"},{"i":"1hQRvGdg9ulaHNA3cbF3wV","n":"Tadahiko Hirano"}],"p":27,"r":"2003-11-27","l":"Walt Disney Records","im":"https://i.scdn.co/image/ab67616d0000b273a53c18dded35eecd56c849fe","ps":[{"i":"37i9dQZF1DX1lolQkPIs5s","n":70,"a":1602788638000,"p":155}],"pp":155},"757":{"i":"7mbwN5OHDcxhgpmQeLGYh4","is":"USWD10525757","n":"You Can Fly! You Can Fly! You Can Fly!","a":[{"i":"0IKotvQocRLaLRkxROzX9U","n":"Natural Notes"}],"p":35,"r":"2003-11-27","l":"Walt Disney Records","im":"https://i.scdn.co/image/ab67616d0000b273a53c18dded35eecd56c849fe","ps":[{"i":"37i9dQZF1DX1lolQkPIs5s","n":63,"a":1602788638000,"p":166}],"pp":166},"833":{"i":"3OApzdwzdJBvkJuTYymYxL","is":"USWD10525833","n":"Ein Traum wird wahr - aus \"Aladdin\"/Deutscher Film-Soundtrack","a":[{"i":"4kkmdWJaq4sXwMsnnnjC3K","n":"Sabine Hettlich"},{"i":"3ri0ApuhNC3iy8yzUoDs2S","n":"Peter Fessler"}],"p":0,"r":"1992-01-01","l":"Walt Disney Records","im":"https://i.scdn.co/image/ab67616d0000b2736bfbdb15c22f07c0e657f21f","ps":[{"i":"37i9dQZF1DXb651y4Mmljv","n":22,"a":1604923413000,"p":433}],"pp":433},"835":{"i":"6gRIh8Hsr3vGsvr59sI8QT","is":"USWD10525835","n":"Sei Hier Gast","a":[{"i":"1QKrprKDJPYZIBnYkBkzRW","n":"Joachim Kemmer"},{"i":"7g8HFAMfGtpguTcHKaClJP","n":"Ingeborg Wellmann"}],"p":46,"r":"2002-01-01","l":"EMI Gold","im":"https://i.scdn.co/image/ab67616d0000b27346d72712531265d68ec1bcac","ps":[{"i":"37i9dQZF1DXb651y4Mmljv","n":41,"a":1604923413000,"p":358}],"pp":358},"836":{"i":"4DyDHvHs3tpcdUJMy2z6Yg","is":"USWD10525836","n":"Unten im Meer","a":[{"i":"7BKapVfxgI266BHEVj44NY","n":"Ron Williams"}],"p":51,"r":"2009-01-01","l":"Walt Disney Records","im":"https://i.scdn.co/image/ab67616d0000b2733f64826feeed6c253f5f83fe","ps":[{"i":"37i9dQZF1DXb651y4Mmljv","n":9,"a":1604923413000,"p":493}],"pp":493},"841":{"i":"5LF5Eq6ouBonZgrZRMrAbJ","is":"USWD10525841","n":"Du hast'n Freund in Mir","a":[{"i":"2gMAioN7m2k5XulfNClMRB","n":"Klaus Lage"}],"p":48,"r":"2009-01-01","l":"Walt Disney Records","im":"https://i.scdn.co/image/ab67616d0000b2733f64826feeed6c253f5f83fe","ps":[{"i":"37i9dQZF1DXb651y4Mmljv","n":23,"a":1604923413000,"p":428}],"pp":428},"938":{"i":"2SDU9Ls1XkvkbmlUgzyx2x","is":"USWD10525938","n":"Les Aristochats","a":[{"i":"3QXjI80udwDSEfxK5BjUXc","n":"Maurice Chevalier"}],"p":40,"r":"2002-01-01","l":"EMI Gold","im":"https://i.scdn.co/image/ab67616d0000b273d7554d2b12d4260f9d0c96ee","ps":[{"i":"37i9dQZF1DX8XxBtyUnC7B","n":14,"a":1602254181000,"p":342}],"pp":342}},"s":[]}