{"d":{"13477":{"i":"7cQglEIv90ThsgOs0Ca5ix","is":"GBSMU8813477","n":"Rutinitas","a":[{"i":"5jwhMbKRR0F4IxyBebhUd6","n":"Roycoustic"}],"p":18,"r":"2020-10-04","l":"Golden Hillz","im":"https://i.scdn.co/image/ab67616d0000b273d542c7a585dfe6ffda5f8709","ps":[{"i":"37i9dQZF1DWTcLP9S6ATGK","n":16,"a":1605200460000,"p":311}],"pp":311},"14708":{"i":"2AAugZhtTGOOCnE0azjpHu","is":"GBSMU8814708","n":"Diamonds","a":[{"i":"7p9ktJF6bgrSyIfz3fnphS","n":"Bustaavat Budit"}],"p":19,"r":"2020-11-11","l":"Bustaavat Budit","im":"https://i.scdn.co/image/ab67616d0000b273d39dd64044b5b06e75f65a1d","ps":[{"i":"37i9dQZF1DWXtcXUwhuzFM","n":58,"a":1605218460000,"p":154}],"pp":154},"14798":{"i":"0xR2v5HbVwLS3cKVtQujpE","is":"GBSMU8814798","n":"MYSKO","a":[{"i":"11jiFlDIkk2TrSubY5lkMB","n":"zla7an"}],"p":17,"r":"2020-10-20","l":"RUSTNING RECORDS","im":"https://i.scdn.co/image/ab67616d0000b27373dea102588347b5cc736042","ps":[{"i":"37i9dQZF1DX5cpU86I7OAy","n":55,"a":1605285072000,"p":149},{"i":"37i9dQZF1DWTECONYYYLCY","n":7,"a":1605285045000,"p":55}],"pp":204},"19626":{"i":"1glSfHrIPx7POzfya0Xe32","is":"GBSMU8819626","n":"Old Way","a":[{"i":"5a3vFEe5TeY6dvzzLVa6cn","n":"Jibs"}],"p":21,"r":"2020-10-30","l":"Young Local Crew","im":"https://i.scdn.co/image/ab67616d0000b273d458d5ba181b70b824e20515","ps":[{"i":"37i9dQZF1DXbrQzAhQxGi4","n":63,"a":1605200460000,"p":74}],"pp":74},"21066":{"i":"7lTXqBURoqMMzzYA6fFF6s","is":"GBSMU8821066","n":"Mood","a":[{"i":"12nEr6QOfSKkiTXjEp8tBB","n":"Koosen"}],"p":70,"r":"2020-10-23","l":"Strange Fruits","im":"https://i.scdn.co/image/ab67616d0000b273f49a17cfe1fb9e9cb79c3a35","ps":[{"i":"37i9dQZF1DXcZDD7cfEKhW","n":13,"a":1605243720000,"p":1573},{"i":"37i9dQZF1DX1lp03JVa0o6","n":12,"a":1605077138000,"p":516},{"i":"37i9dQZF1DX1OxnjWYRVU0","n":15,"a":1605222120000,"p":403},{"i":"37i9dQZF1DWTwCImwcYjDL","n":19,"a":1605197080000,"p":399},{"i":"37i9dQZF1DWZCdOD1jAvLL","n":0,"a":1605290324000,"p":281},{"i":"37i9dQZF1DX7CfwQr5vk7g","n":38,"a":1605207205000,"p":268},{"i":"37i9dQZF1DXaqIZ7YXxc6o","n":32,"a":1605186060000,"p":235},{"i":"37i9dQZF1DWWOGXILUAh53","n":50,"a":1603439980000,"p":94}],"pp":3769},"24506":{"i":"1joDf8n61wH3eLcAql8sPT","is":"GBSMU8824506","n":"Itan","a":[{"i":"5QjGFe0TnTyU3FF44b0vx4","n":"Fax"}],"p":19,"r":"2020-11-02","l":"Fax","im":"https://i.scdn.co/image/ab67616d0000b2736e853abde480e5c1b1e4e6a2","ps":[{"i":"37i9dQZF1DWZ7mSWCFIT7v","n":7,"a":1605195567000,"p":155}],"pp":155},"25535":{"i":"1S2y8lwYUjaV2ExDzJCmN3","is":"GBSMU8825535","n":"Fighting To Life","a":[{"i":"2Wg88JeVLshKfXx6pvke0B","n":"Pempek Rocket"}],"p":7,"r":"2020-10-06","l":"Dope Stereo","im":"https://i.scdn.co/image/ab67616d0000b27364c1f36ab6be15c9321ef578","ps":[{"i":"37i9dQZF1DX5tw1xuXSiCW","n":10,"a":1605238450000,"p":204}],"pp":204},"29738":{"i":"57NoTa96L31Sbp8FRv3PkJ","is":"GBSMU8829738","n":"Sweet Lullaby","a":[{"i":"733pYGuQ9xwCh15uK2VWT1","n":"offrami"},{"i":"4gmndqcVVyxmzgOunTiuAD","n":"Mougleta"}],"p":56,"r":"2020-10-23","l":"Lilly Era","im":"https://i.scdn.co/image/ab67616d0000b273e6428e9a336e9b4176fd44e9","ps":[{"i":"37i9dQZF1DWUq3wF0JVtEy","n":50,"a":1603430106000,"p":515},{"i":"37i9dQZF1DXdIpacQDPDV5","n":56,"a":1605289767000,"p":298}],"pp":813},"36016":{"i":"38SQyUEexla3OZy6rNQ7ID","is":"GBSMU8836016","n":"Memories","a":[{"i":"6Q84rx53mnm7Wgad5xhAsg","n":"JOVEO"},{"i":"5tF4j2R7iNOIFdmpmEsn3s","n":"Mike Gudmann"},{"i":"2ghlJsDAq3yMB04J7AgfwJ","n":"Popcorn!"}],"p":42,"r":"2020-10-23","l":"GLWRRCRDS","im":"https://i.scdn.co/image/ab67616d0000b2733349e5f0c8c8ade85c1ec065","ps":[{"i":"37i9dQZF1DWUq3wF0JVtEy","n":42,"a":1603430106000,"p":558}],"pp":558},"44480":{"i":"0tMiZhYdNvzgN0EQkH3QA1","is":"GBSMU8844480","n":"Hatchlings","a":[{"i":"0GJ3FYu5TXpDjqvPs9iA4u","n":"Fets"},{"i":"6qTV5zSs0XxRpVhb1ADE0H","n":"Sorbet"},{"i":"4xB6Wfj8CgJaQc86Zyxld0","n":"Kuku"}],"p":55,"r":"2020-10-23","l":"Strange Fruits","im":"https://i.scdn.co/image/ab67616d0000b273bdaf1fa3f3e5e9eb4c6f7a2f","ps":[{"i":"37i9dQZF1DWWQRwui0ExPn","n":47,"a":1605247260000,"p":1184}],"pp":1184},"44768":{"i":"420MoV0Uz1PXprFhcVDSHH","is":"GBSMU8844768","n":"Night Like This","a":[{"i":"2Ie3P7oklbSFxfrGtrkT9W","n":"Orange Stick"},{"i":"48QpIkzC2yRCUCvNvOVZqD","n":"Avocuddle"},{"i":"0jRbAcpQhqQJWgtSRG6oYy","n":"Green Bull"}],"p":54,"r":"2020-10-30","l":"Strange Fruits","im":"https://i.scdn.co/image/ab67616d0000b273940efc5181f3f02775fc051b","ps":[{"i":"37i9dQZF1DWWQRwui0ExPn","n":15,"a":1605247260000,"p":1633}],"pp":1633},"46237":{"i":"1gCdDceCzwWmkXUsFrDzNt","is":"GBSMU8846237","n":"Te Amo y Te Odio","a":[{"i":"2iA56rE7fZUnD4GdsSUj3G","n":"Galvan Real"}],"p":56,"r":"2020-10-09","l":"Galvan Real","im":"https://i.scdn.co/image/ab67616d0000b27344ca04cf907bbba38c0bed7b","ps":[{"i":"37i9dQZF1DWZMtkg0cMXbp","n":2,"a":1605222120000,"p":352}],"pp":352},"49000":{"i":"6hDY73hAEcXvauzrNElqmg","is":"GBSMU8849000","n":"my future","a":[{"i":"3WTz0blF6VEVG310Lfzn6Z","n":"chloe evee"},{"i":"1Dl5r4vde6tLH3VKTemadE","n":"SAMI"}],"p":40,"r":"2020-10-22","l":"11:11 Music Group","im":"https://i.scdn.co/image/ab67616d0000b27368bac687ef04163921638f1c","ps":[{"i":"37i9dQZF1DXb67OkZ6150Z","n":13,"a":1603479720000,"p":341}],"pp":341},"53986":{"i":"41FwU4Mqh7TZWSL0OCZYUe","is":"GBSMU8853986","n":"Every Day And Every Night - soft rock single mix","a":[{"i":"57QKB7iuUXLFEWqWBvCmf8","n":"Hank Rosse & The Light Beyond"}],"p":8,"r":"2020-11-06","l":"HR Records","im":"https://i.scdn.co/image/ab67616d0000b273d9835dad0636b96bf782f313","ps":[{"i":"37i9dQZF1DX1mmgryvoR0n","n":17,"a":1605040196000,"p":41}],"pp":41},"64758":{"i":"66JOrmAiPchIFXuDCiV5gW","is":"GBSMU8864758","n":"done fighting","a":[{"i":"1N8Y4kaIF0ktxmylgsvUiY","n":"Rewind"},{"i":"33FWu1JTA73HpPE2tBiwNX","n":"Addict."},{"i":"0Tw99NzcM3Y2t7Q2q88Xss","n":"Julia Alexa"}],"p":41,"r":"2020-10-30","l":"11:11 Music Group","im":"https://i.scdn.co/image/ab67616d0000b273fe6d10d155a2bdfeed431874","ps":[{"i":"37i9dQZF1DX9FcC8tuoPzi","n":2,"a":1605222060000,"p":332}],"pp":332},"68877":{"i":"2sDA5CpPm9H20LzsXXbSbZ","is":"GBSMU8868877","n":"All The Things She Said","a":[{"i":"5f5mH9BDkeyXmDbzevu38d","n":"Alfons"},{"i":"2ghlJsDAq3yMB04J7AgfwJ","n":"Popcorn!"}],"p":23,"r":"2020-11-13","l":"GLWRRCRDS","im":"https://i.scdn.co/image/ab67616d0000b273556d7ea099df81f514a8bfa2","ps":[{"i":"37i9dQZF1DX1OxnjWYRVU0","n":34,"a":1605222120000,"p":333}],"pp":333},"73105":{"i":"41yS3MD3Xdnmp1sVVagt3F","is":"GBSMU8873105","n":"Guritan Kabudul","a":[{"i":"1I5NsBmovVRwam5At3VDLL","n":"Guritan Kabudul"}],"p":7,"r":"2020-10-08","l":"Golden Hillz","im":"https://i.scdn.co/image/ab67616d0000b273e6ad7a45e1198d99bc620c95","ps":[{"i":"37i9dQZF1DXdKj73Pzxb5r","n":33,"a":1605246943000,"p":39}],"pp":39},"73646":{"i":"3TKYpVvhTKoKl5vIrX96AD","is":"GBSMU8873646","n":"Prophecy","a":[{"i":"4xt0qH1NubQexyAzDa9UlR","n":"Castion"}],"p":52,"r":"2020-10-23","l":"Bass House Music","im":"https://i.scdn.co/image/ab67616d0000b273340d45478b6b4dfb284a5fa6","ps":[{"i":"37i9dQZF1DWUq3wF0JVtEy","n":26,"a":1603909187000,"p":656},{"i":"37i9dQZF1DX0hvSv9Rf41p","n":33,"a":1604638860000,"p":649},{"i":"37i9dQZF1DX2VvACCrgjrt","n":17,"a":1604638980000,"p":62}],"pp":1367},"77006":{"i":"07a6G9s49ocCZ6ayLQYklP","is":"GBSMU8877006","n":"Outside","a":[{"i":"6lc0muqqPZVQsaTsNCyuRa","n":"Feb"},{"i":"3AGYevFLXCIrY67MwyAjW2","n":"Salasnich"},{"i":"4rxkYdxnD8OLxuwqKiwmw9","n":"Lexie"}],"p":52,"r":"2020-11-06","l":"Strange Fruits","im":"https://i.scdn.co/image/ab67616d0000b27306d1b93da7c2b8fc30fb0e49","ps":[{"i":"37i9dQZF1DX1OxnjWYRVU0","n":37,"a":1605222120000,"p":323}],"pp":323},"78521":{"i":"2XqrW3DckGuX40QWSp3QnZ","is":"GBSMU8878521","n":"Only Way","a":[{"i":"1kPCI44Jh0btRRRHjouPSc","n":"Natio"},{"i":"776UugG4CdQlYfsEUVCRqb","n":"Nina Carr"}],"p":47,"r":"2020-11-06","l":"Spectrum Recordings","im":"https://i.scdn.co/image/ab67616d0000b273588fc037e809f4d35905d4fb","ps":[{"i":"37i9dQZF1DWSf2RDTDayIx","n":5,"a":1604640540000,"p":1121}],"pp":1121},"78964":{"i":"7aK6OPQHN3A9xC7uneiN9H","is":"GBSMU8878964","n":"Reasons","a":[{"i":"78Bbgb8kaIDnW3GCeWlDDa","n":"Newera"}],"p":21,"r":"2020-11-13","l":"Youth Energy","im":"https://i.scdn.co/image/ab67616d0000b2734c78a225d813498484f46927","ps":[{"i":"37i9dQZF1DXdVmhVVRZJ3I","n":0,"a":1605287782000,"p":480}],"pp":480},"83511":{"i":"44540FXlRgSIn2cziKYRN2","is":"GBSMU8883511","n":"Cha Cha Slide","a":[{"i":"0jRbAcpQhqQJWgtSRG6oYy","n":"Green Bull"},{"i":"12nEr6QOfSKkiTXjEp8tBB","n":"Koosen"},{"i":"0GJ3FYu5TXpDjqvPs9iA4u","n":"Fets"}],"p":40,"r":"2020-11-13","l":"Strange Fruits","im":"https://i.scdn.co/image/ab67616d0000b27324340e098f8e075474708eed","ps":[{"i":"37i9dQZF1DX9Bom9R0tCgx","n":1,"a":1605222060000,"p":421},{"i":"37i9dQZF1DX1OxnjWYRVU0","n":22,"a":1605222120000,"p":376},{"i":"37i9dQZF1DX6uIc2aogDNQ","n":6,"a":1605499260000,"p":219},{"i":"37i9dQZF1DX4dvQTO6iy9m","n":22,"a":1605499260000,"p":148}],"pp":1164},"87126":{"i":"02MkiCuK4vBsHu9Tb5d80H","is":"GBSMU8887126","n":"Fire","a":[{"i":"2ghlJsDAq3yMB04J7AgfwJ","n":"Popcorn!"},{"i":"0eGQLgDJaGfvvKv7spAgqX","n":"MARE"},{"i":"5tF4j2R7iNOIFdmpmEsn3s","n":"Mike Gudmann"}],"p":29,"r":"2020-10-30","l":"PopcornMusic","im":"https://i.scdn.co/image/ab67616d0000b27300797937ca0652b3723b1926","ps":[{"i":"37i9dQZF1DX5FlZmJ3JWL1","n":1,"a":1605270928000,"p":720}],"pp":720},"05911":{"i":"54bBoa59wxXmxjND5AQcWn","is":"GBSMU8805911","n":"Why Do I","a":[{"i":"6Cubdky3Aaaaxc3sn5C32N","n":"Kaan Pars"},{"i":"7vMDKdgSZ2Scn4uzFdTDyZ","n":"Emie"}],"p":39,"r":"2020-11-13","l":"Spectrum Recordings","im":"https://i.scdn.co/image/ab67616d0000b27344cbb80c76ff3a0ae4b4b351","ps":[{"i":"37i9dQZF1DXd8Yptw1g5FC","n":14,"a":1605216109000,"p":319},{"i":"37i9dQZF1DWXxFrpWsbL4P","n":6,"a":1605291235000,"p":234}],"pp":553},"06524":{"i":"6hODyf8EfADdykWtBGrWJa","is":"GBSMU8806524","n":"Palangga Tika","a":[{"i":"1jhx24T3Mf7OhUDt57Ouzw","n":"Emping"}],"p":12,"r":"2020-11-06","l":"KB Records","im":"https://i.scdn.co/image/ab67616d0000b273f5817fb12bf00929065f898d","ps":[{"i":"37i9dQZF1DXd41OiKoLJY1","n":67,"a":1605196860000,"p":103}],"pp":103}},"s":[]}