{"d":{"A7d9(Ob(K(O(I(S(H(Z(Zcw(Pl7k(I4":{"i":"4A7d9ObKOISHZZcwPl7kI4","n":"¿Y Qué Pasó Anoche?","a":[{"i":"7GIjPB112ZItDWPcDSG5Ze","n":"El Café de la Mañana"}],"p":0,"r":null,"im":"https://i.scdn.co/image/f5ccbae72ebfe48d99d83c93c12fe80b5e5c0e30","ps":[{"i":"37i9dQZF1DX2u8dMimQXxa","n":0,"a":1604595310000,"p":55}],"pp":55},"D(Rb(R(Tp(Nso(Si(H3(O(P(R2d4(Yo":{"i":"4DRbRTpNsoSiH3OPR2d4Yo","n":"Mujeres STEM: Karen Liz Mejía, Youtuber en La Ciencia Detrás De ","a":[{"i":"35lYVEUcRR6bmXHjJUCJDn","n":"Epic Queen"}],"p":0,"r":null,"im":"https://i.scdn.co/image/5948976ec5a0f2b7ed26c28e82640ff3e86ecd41","ps":[{"i":"37i9dQZF1DX2u8dMimQXxa","n":1,"a":1604595310000,"p":55}],"pp":55},"Y(Am(Kc(Dh(Iey1(Q8dol(J(H(A(S4":{"i":"4YAmKcDhIey1Q8dolJHAS4","n":"Halloween-Special: Der Lieferant & Das russische Schlafexperiment","a":[{"i":"2p4tkQK4wCSiMca1JmDPYQ","n":"Menschen und Monster"}],"p":0,"r":null,"im":"https://i.scdn.co/image/f6306126850cc9957de5b551d69515760f88518c","ps":[{"i":"37i9dQZF1DWY260I2XvMMJ","n":7,"a":1604403675000,"p":183}],"pp":183},"Lcz9(Rw0g(H(Cf3a9(X(K(Q(Ah(Tr":{"i":"4Lcz9Rw0gHCf3a9XKQAhTr","n":"„Vorsicht — Greisverkehr!“","a":[{"i":"4vGrYFWyoBuZyZCdCytwfO","n":"Dem Tod auf der Spur"}],"p":0,"r":null,"im":"https://i.scdn.co/image/8b8ed481471bd1ae99b4808e3184e48b60f897e3","ps":[{"i":"37i9dQZF1DWY260I2XvMMJ","n":8,"a":1604403675000,"p":181}],"pp":181},"X(Ii(R(We(G(D(Rg(W(Tg5q9(Sacqi":{"i":"4XIiRWeGDRgWTg5q9Sacqi","n":"4. What They Knew","a":[{"i":"2CG58YDV7p8vamvYq7WhgK","n":"The Nurse"}],"p":0,"r":null,"im":"https://i.scdn.co/image/f45af2cb62509d6c4c9d72a2d1b6636eb8afa934","ps":[{"i":"37i9dQZF1DWY5lzjtRUfdF","n":7,"a":1605053444000,"p":45}],"pp":45},"A(Xoc(Z(I(E(Xl(V(X5(B(Foh(Z4(Klb":{"i":"4AXocZIEXlVX5BFohZ4Klb","n":"REPÚBLICA DEBOCHEVIQUE 2020.2 | feat Jair Me Arrependi + Bolsoregrets + Victor Camejo + Tesoureiros + Normose","a":[{"i":"2w3IfCyn2cAVrSrzVkwTcj","n":"Hoje Tem Podcast"}],"p":0,"r":null,"im":"https://i.scdn.co/image/307fcae5f8aa6e885cef2288bc052129f9d7b5f2","ps":[{"i":"37i9dQZF1DX5sOH3YgmxsX","n":0,"a":1605289489000,"p":80}],"pp":80},"O(Wb03ywse(Z(D(N3q(X(Xn7p(Tp":{"i":"4OWb03ywseZDN3qXXn7pTp","n":"S3 Episode 1: Kojey Radical","a":[{"i":"49k0UoXBhqOUhPMfnjnicp","n":"Hip Hop Saved My Life with Romesh Ranganathan"}],"p":0,"r":null,"im":"https://i.scdn.co/image/391112aead24eb1db7a00aa697a7bdd53ce269cf","ps":[{"i":"37i9dQZF1DXdlkPQJ1PlTQ","n":2,"a":1604984760000,"p":278},{"i":"37i9dQZF1DWSxZ7JEayeSs","n":1,"a":1604995080000,"p":136}],"pp":414},"U(Y(Va(Ly03v(Cvxu(K(Uu2n1(G5":{"i":"4UYVaLy03vCvxuKUu2n1G5","n":"Phillip Schofield","a":[{"i":"1J6Ddy4dcXjFZDmWQs3Pu0","n":"Happy Place"}],"p":0,"r":null,"im":"https://i.scdn.co/image/76cc50a3bc75490b44a264df090d01d17c75d786","ps":[{"i":"37i9dQZF1DXdjkUsPkITjv","n":0,"a":1603706169000,"p":26}],"pp":26},"A(K(K(F(Q699(D(F7f8q(Knl(Bjh(R":{"i":"4AKKFQ699DF7f8qKnlBjhR","n":"Amrou Al-Kadhi | IN-BETWEEN","a":[{"i":"3WvaFOFAUccia2ULq9fzQG","n":"Anthems"}],"p":0,"r":null,"im":"https://i.scdn.co/image/d7970d219a46716c87f2c9a838a6c33d36e249af","ps":[{"i":"37i9dQZF1DXdjkUsPkITjv","n":5,"a":1591620115000,"p":25}],"pp":25},"Txf(Zzrq0d(H2(Wmfl4d(Aj(N9":{"i":"4TxfZzrq0dH2Wmfl4dAjN9","n":"Ella's Lullaby","a":[{"i":"7eHcKVhaxOOTKJFZuu3x1h","n":"Enno Aare"}],"p":55,"r":"2016-11-28","l":"Enno Aare","im":"https://i.scdn.co/image/ab67616d0000b273a250604d6d9f28e94cc015ec","ps":[{"i":"37i9dQZF1DX05Zqxyo07cQ","n":316,"a":1605185132000,"p":36},{"i":"37i9dQZF1DWWecqh2y5eD4","n":341,"a":1605186289000,"p":7}],"pp":43},"T(N(M(K(Asyn(Ch(Sax(D(Z(Tf8k0(N":{"i":"4TNMKAsynChSaxDZTf8k0N","n":" So Why Are People Watching Less Sports? ","a":[{"i":"48blK5AoWuyEJc9L9TX9OM","n":"Edge of Sports"}],"p":0,"r":null,"im":"https://i.scdn.co/image/e8d7759adaa2fbecbb5a93b310a72aea922a20bc","ps":[{"i":"37i9dQZF1DX9Rk84TK5Nwc","n":12,"a":1603112609000,"p":76}],"pp":76},"O(I(G4(Bp(T0ihlv(Fb(Jehv(I7(L":{"i":"4OIG4BpT0ihlvFbJehvI7L","n":"Morning in America - Part 1 ","a":[{"i":"7zB5zDLUEfyaTr1dIrm1Y5","n":"Bobbo Supreme"}],"p":0,"r":null,"im":"https://i.scdn.co/image/84a8c212a49e7734613849c921cc109d04de33d0","ps":[{"i":"37i9dQZF1DX1ywXghfWcTX","n":7,"a":1603080360000,"p":224}],"pp":224},"F(X6gs(K(B7fwc(H(Hp(Xd(L(R(Khv":{"i":"4FX6gsKB7fwcHHpXdLRKhv","n":"Letting Go of Anxiety","a":[{"i":"4bSTeVDsXWKQCRptxuZnVQ","n":"Meditation Minis Podcast"}],"p":0,"r":null,"im":"https://i.scdn.co/image/c3989bb31c75be5befc87140828e8042c8f75e63","ps":[{"i":"37i9dQZF1DX1mvxijKNTk9","n":1,"a":1605054917000,"p":69}],"pp":69},"Iidjeo(Nw(Wd(Nzi1sd(D(A(Yw(Y":{"i":"4IidjeoNwWdNzi1sdDAYwY","n":"Your Shortcut to... Vladimir Putin","a":[{"i":"1ANvW9TAd2mg2rrHw7pQDv","n":"Squiz Shortcuts"}],"p":0,"r":null,"im":"https://i.scdn.co/image/b54f7b8c817b998aa7d44f115e21abbf9634d182","ps":[{"i":"37i9dQZF1DX1mvxijKNTk9","n":2,"a":1605054917000,"p":69}],"pp":69},"Tn8(Avy(Qo(W4l(Yq(Rp(S(Q(Y(E(A(J":{"i":"4Tn8AvyQoW4lYqRpSQYEAJ","n":"Confessions of a climate scientist","a":[{"i":"1KCKmwzycA9VOBDJCQ4S7Y","n":"TEDx SHORTS"}],"p":0,"r":null,"im":"https://i.scdn.co/image/fcd54729a2d017dc9904735e06c82157b4233d5f","ps":[{"i":"37i9dQZF1DX1mvxijKNTk9","n":3,"a":1605054917000,"p":68}],"pp":68},"P(I(T3xg(S(Ne(I78(Db(T(Ud(K769":{"i":"4PIT3xgSNeI78DbTUdK769","n":"How do bees talk to each other?","a":[{"i":"5WPQenVFCyOue3YzRoDcV8","n":"Maddie's Sound Explorers"}],"p":0,"r":null,"im":"https://i.scdn.co/image/2ceb1db55bee04a3b9c98276bb4672417991b1d2","ps":[{"i":"37i9dQZF1DXbECFsNMysNX","n":3,"a":1596627263000,"p":29}],"pp":29},"E(C(V(Hb(T(Kv(S(F(Y(Gm(E9(A(Rb(Dbx":{"i":"4ECVHbTKvSFYGmE9ARbDbx","n":"Toilets","a":[{"i":"5VWLRdycGKKHBPvBiQGWzj","n":"The Fact Detectives"}],"p":0,"r":null,"im":"https://i.scdn.co/image/437f5a90b2b69a5915fe1c95d58b5c391b978d4f","ps":[{"i":"37i9dQZF1DXbECFsNMysNX","n":5,"a":1602055545000,"p":28}],"pp":28},"V(H(Iz(C(I(A9(J(Ej11(Cu(Qt8(V4j":{"i":"4VHIzCIA9JEj11CuQt8V4j","n":"シンガロング機能が新登場","a":[{"i":"0cSvtUuwNbMqDAIezFm9c9","n":"What's New With Spotify"}],"p":0,"r":null,"im":"https://i.scdn.co/image/4a9e47e76d3d6d9d0a76b51bbfc1c44285397d02","ps":[{"i":"37i9dQZF1DWUnxWoAqoCag","n":0,"a":1602133202000,"p":287},{"i":"37i9dQZF1DWSGR2XLfOnfo","n":0,"a":1602133718000,"p":109},{"i":"37i9dQZF1DX3f3gm9VK7fL","n":0,"a":1602055802000,"p":100},{"i":"37i9dQZF1DXbXiYi0xyeiI","n":0,"a":1602133697000,"p":77},{"i":"37i9dQZF1DWUNxtY74ScrL","n":0,"a":1602133743000,"p":56}],"pp":629},"Vu09(Tiue(A(Svmxn6(Ie(T(Qm(T":{"i":"4Vu09TiueASvmxn6IeTQmT","n":"Merry Christmas Mr. Lawrence","a":[{"i":"3kTQiUxeIBkaXlOug0xXXX","n":"David West"}],"p":31,"r":"2016-11-28","l":"David West","im":"https://i.scdn.co/image/9d10f41dc01fbe72347039678503e523b26b33a7","ps":[{"i":"37i9dQZF1DXa6DEdeHsDKX","n":91,"a":1603460639000,"p":114}],"pp":114},"B(Eck(J(Teo4br(Ex(Q(R6(B(Y(Vp(W":{"i":"4BEckJTeo4brExQR6BYVpW","n":"Lo Que No Te Enseñan en Harvard - #137 - Un Resumen de Libros para Emprendedores","a":[{"i":"0qXuVDCYF8HvkEynJwHULb","n":"Libros para Emprendedores"}],"p":0,"r":null,"im":"https://i.scdn.co/image/77071646f5c88acc09ed5750b4ca769dbfa88170","ps":[{"i":"37i9dQZF1DWUHYRPM69PPw","n":3,"a":1587154323000,"p":58}],"pp":58},"Kq(Iu(J(R2lio(Ib(X1j(Sw(Y7v(H":{"i":"4KqIuJR2lioIbX1jSwY7vH","n":"INTÉNTALO Y CÁGALA RAPIDO","a":[{"i":"5eGKwDdheB8QFmyH9JG2Uw","n":"COSAS"}],"p":0,"r":null,"im":"https://i.scdn.co/image/f49e6319a8975bcb3ad007e99ac1e703212dca31","ps":[{"i":"37i9dQZF1DWUHYRPM69PPw","n":18,"a":1599234677000,"p":50}],"pp":50},"Ofmhel(E2p(Puy(Ulhisz(Hpz":{"i":"4OfmhelE2pPuyUlhiszHpz","n":"Nightmare breakups","a":[{"i":"7lycbEakhDPCfa6xChvFHT","n":"Love etc."}],"p":0,"r":null,"im":"https://i.scdn.co/image/71af829e02a27eb44cc1646dbcd25423138192c2","ps":[{"i":"37i9dQZF1DX4Glla9HCJfl","n":3,"a":1604926860000,"p":43}],"pp":43},"E5s(L(Xna(I0(Zlh(Tn(Bddd(R(Fj":{"i":"4E5sLXnaI0ZlhTnBdddRFj","n":"Are the Kids Alright?","a":[{"i":"4KI3PtZaWJbAWK89vgttoU","n":"Your Undivided Attention"}],"p":0,"r":null,"im":"https://i.scdn.co/image/dba1571b95d308960adfb405360a81d2ea69e2ac","ps":[{"i":"37i9dQZF1DX4Glla9HCJfl","n":4,"a":1604926860000,"p":43}],"pp":43},"X(J1vre(P(P1(Tx(Bn7(Wy(Wa(C49":{"i":"4XJ1vrePP1TxBn7WyWaC49","n":"The Waltz Between Us","a":[{"i":"3kfHheH2kjb3gsLwSowrdb","n":"Tonie Green"}],"p":44,"r":"2016-07-31","l":"QLP","im":"https://i.scdn.co/image/ab67616d0000b2736f873a84900c79b37643f53a","ps":[{"i":"37i9dQZF1DX47ov4h4oSjW","n":55,"a":1605300783000,"p":179}],"pp":179},"Rxx(Ugnc2(Jpzk(Y(Mh(R(E927b":{"i":"4RxxUgnc2JpzkYMhRE927b","n":"Delta Green Episode 5: Potluck! (With Cassie and Samantha of The LovelyCraftians)","a":[{"i":"32yzWJ4bhKiNBBMKaEh8e0","n":"Tabletop Potluck"}],"p":0,"r":null,"im":"https://i.scdn.co/image/a3b46fe13b5e51475a38585c1f76921b8c86a1de","ps":[{"i":"37i9dQZF1DX5qDPWCwzjPd","n":7,"a":1600437517000,"p":57}],"pp":57},"A(K(A(Pn(L(Ay(J(J(H(Qji(Lus3(Mci":{"i":"4AKAPnLAyJJHQjiLus3Mci","n":"Our Top 25 SEGA Master System Games","a":[{"i":"36VY08IEghBsmxCY49Smiy","n":"Arcade Attack Retro Gaming Podcast"}],"p":0,"r":null,"im":"https://i.scdn.co/image/9674e0c246ce850e84b006acdb3eff8096a28629","ps":[{"i":"37i9dQZF1DX5qDPWCwzjPd","n":10,"a":1600437517000,"p":55}],"pp":55},"Kx(U(Er(Rt1rl(Eks(Fw(U(Wp6w(W":{"i":"4KxUErRt1rlEksFwUWp6wW","n":"Episode 82 David Ajao: Is It OK To Agree With Piers Morgan?","a":[{"i":"2vpjFGAqcXebE2O5mQLLi7","n":"Dane Baptiste Questions Everything"}],"p":0,"r":null,"im":"https://i.scdn.co/image/c37e197d0a4bb8786b6162624941006a1a5bd2a6","ps":[{"i":"37i9dQZF1DWTPl5WkzxYC9","n":1,"a":1604504911000,"p":115}],"pp":115},"N2u(I(C(B(R(Brhpf(J06(I1s(Ns(R":{"i":"4N2uICBRBrhpfJ06I1sNsR","n":"The 2 Johnnies","a":[{"i":"4CQfEct1b7aotdVB4T4gLC","n":"The Laughs Of Your Life with Doireann Garrihy"}],"p":0,"r":null,"im":"https://i.scdn.co/image/cecf30100b384818057af6701a6bbc7563d2d2cf","ps":[{"i":"37i9dQZF1DWTPl5WkzxYC9","n":5,"a":1604569010000,"p":110}],"pp":110},"C6(Kxw9b(O470x(Ga(Dy(K(H7(N7":{"i":"4C6Kxw9bO470xGaDyKH7N7","n":"Especial Inventoras: Si puedes imaginarlo, puedes crearlo","a":[{"i":"6RVbSxq5IErJLutO3ukgG6","n":"Aula365"}],"p":0,"r":null,"im":"https://i.scdn.co/image/d0290c2f58041c08a16c18779757eaf6a3f3fbd3","ps":[{"i":"37i9dQZF1DWW8zRsEZD80f","n":7,"a":1604937304000,"p":78}],"pp":78},"De(Vb0(J(Qm(Hr653b7(Eyr(J(V1":{"i":"4DeVb0JQmHr653b7EyrJV1","n":"#75 - La trampa de las metas","a":[{"i":"0cyoJ0gr5wgJh2OWbOCHZj","n":"Diego Dreyfus"}],"p":0,"r":null,"im":"https://i.scdn.co/image/fdc0327265d7356ccc26eea63beb8a6a92265332","ps":[{"i":"37i9dQZF1DWZSjQC8EbKpR","n":6,"a":1603295424000,"p":95}],"pp":95},"Lb(Ks(X(Re(U(R6(F(Ilm(Y1q(In(J(P":{"i":"4LbKsXReUR6FIlmY1qInJP","n":"Girl, Andá a Terapia S01E09 - Hay Cosas que No Están en Tu Control","a":[{"i":"1WjEo53591zEBLfEL4Zhl2","n":"Girl, Andá a Terapia"}],"p":0,"r":null,"im":"https://i.scdn.co/image/6324076b84de7ca66c133b99ca5e77335be13975","ps":[{"i":"37i9dQZF1DX6Z4GnyWCQcq","n":2,"a":1603917767000,"p":14}],"pp":14},"O(L(O(Uew5(Hq8w(Xk(I1(Y(A(S(U(W(F":{"i":"4OLOUew5Hq8wXkI1YASUWF","n":"新概念提唱型投稿コーナー（シアター 一期一会） ","a":[{"i":"3Xvbka6gUb0Sxsf4Iiu8qJ","n":"TBSラジオ「アフター6ジャンクション」"}],"p":0,"r":null,"im":"https://i.scdn.co/image/2b42219fa08d3dd865c11b1cf31959d6ebfbdb17","ps":[{"i":"37i9dQZF1DWXbLT8Cnrn37","n":32,"a":1604664060000,"p":52}],"pp":52}},"s":[]}